Workbook

Sheet Сравнение
A1: Сделка | B1: Категория | C1: Город | D1: ЦИАН | E1: Яндекс | F1: Авито | G1: Домклик | H1: Лидер
A2: Продажа | B2: Квартиры — всего | C2: 🇷🇺 Вся Россия | D2: =SUMIFS(ЦИАН!$D:$D,ЦИАН!$A:$A,"Продажи квартир",ЦИАН!$B:$B,"Квартиры в новостройках",ЦИАН!$C:$C,$C2)+SUMIFS(ЦИАН!$D:$D,ЦИАН!$A:$A,"Продажи квартир",ЦИАН!$B:$B,"Квартиры во вторичке",ЦИАН!$C:$C,$C2) | E2: =SUMIFS(Яндекс!$D:$D,Яндекс!$A:$A,"Купить",Яндекс!$B:$B,"Квартира в новостройке",Яндекс!$C:$C,$C2)+SUMIFS(Яндекс!$D:$D,Яндекс!$A:$A,"Купить",Яндекс!$B:$B,"Квартира во вторичке",Яндекс!$C:$C,$C2) | F2: =SUMIFS(Авито!$E:$E,Авито!$A:$A,"Продажа",Авито!$B:$B,"Квартиры",Авито!$C:$C,$C2) | G2: =SUMIFS(Домклик!$D:$D,Домклик!$A:$A,"Покупка",Домклик!$B:$B,"Квартиры",Домклик!$C:$C,$C2) | H2: =IFERROR(INDEX($D$1:$G$1,MATCH(MAX(D2:G2),D2:G2,0)),"")
A3: Продажа | B3: Квартиры — всего | C3: Москва | D3: =SUMIFS(ЦИАН!$D:$D,ЦИАН!$A:$A,"Продажи квартир",ЦИАН!$B:$B,"Квартиры в новостройках",ЦИАН!$C:$C,$C3)+SUMIFS(ЦИАН!$D:$D,ЦИАН!$A:$A,"Продажи квартир",ЦИАН!$B:$B,"Квартиры во вторичке",ЦИАН!$C:$C,$C3) | E3: =SUMIFS(Яндекс!$D:$D,Яндекс!$A:$A,"Купить",Яндекс!$B:$B,"Квартира в новостройке",Яндекс!$C:$C,$C3)+SUMIFS(Яндекс!$D:$D,Яндекс!$A:$A,"Купить",Яндекс!$B:$B,"Квартира во вторичке",Яндекс!$C:$C,$C3) | F3: =SUMIFS(Авито!$E:$E,Авито!$A:$A,"Продажа",Авито!$B:$B,"Квартиры",Авито!$C:$C,$C3) | G3: =SUMIFS(Домклик!$D:$D,Домклик!$A:$A,"Покупка",Домклик!$B:$B,"Квартиры",Домклик!$C:$C,$C3) | H3: =IFERROR(INDEX($D$1:$G$1,MATCH(MAX(D3:G3),D3:G3,0)),"")
A4: Продажа | B4: Квартиры — всего | C4: Санкт-Петербург | D4: =SUMIFS(ЦИАН!$D:$D,ЦИАН!$A:$A,"Продажи квартир",ЦИАН!$B:$B,"Квартиры в новостройках",ЦИАН!$C:$C,$C4)+SUMIFS(ЦИАН!$D:$D,ЦИАН!$A:$A,"Продажи квартир",ЦИАН!$B:$B,"Квартиры во вторичке",ЦИАН!$C:$C,$C4) | E4: =SUMIFS(Яндекс!$D:$D,Яндекс!$A:$A,"Купить",Яндекс!$B:$B,"Квартира в новостройке",Яндекс!$C:$C,$C4)+SUMIFS(Яндекс!$D:$D,Яндекс!$A:$A,"Купить",Яндекс!$B:$B,"Квартира во вторичке",Яндекс!$C:$C,$C4) | F4: =SUMIFS(Авито!$E:$E,Авито!$A:$A,"Продажа",Авито!$B:$B,"Квартиры",Авито!$C:$C,$C4) | G4: =SUMIFS(Домклик!$D:$D,Домклик!$A:$A,"Покупка",Домклик!$B:$B,"Квартиры",Домклик!$C:$C,$C4) | H4: =IFERROR(INDEX($D$1:$G$1,MATCH(MAX(D4:G4),D4:G4,0)),"")
A5: Продажа | B5: Квартиры — всего | C5: Новосибирск | D5: =SUMIFS(ЦИАН!$D:$D,ЦИАН!$A:$A,"Продажи квартир",ЦИАН!$B:$B,"Квартиры в новостройках",ЦИАН!$C:$C,$C5)+SUMIFS(ЦИАН!$D:$D,ЦИАН!$A:$A,"Продажи квартир",ЦИАН!$B:$B,"Квартиры во вторичке",ЦИАН!$C:$C,$C5) | E5: =SUMIFS(Яндекс!$D:$D,Яндекс!$A:$A,"Купить",Яндекс!$B:$B,"Квартира в новостройке",Яндекс!$C:$C,$C5)+SUMIFS(Яндекс!$D:$D,Яндекс!$A:$A,"Купить",Яндекс!$B:$B,"Квартира во вторичке",Яндекс!$C:$C,$C5) | F5: =SUMIFS(Авито!$E:$E,Авито!$A:$A,"Продажа",Авито!$B:$B,"Квартиры",Авито!$C:$C,$C5) | G5: =SUMIFS(Домклик!$D:$D,Домклик!$A:$A,"Покупка",Домклик!$B:$B,"Квартиры",Домклик!$C:$C,$C5) | H5: =IFERROR(INDEX($D$1:$G$1,MATCH(MAX(D5:G5),D5:G5,0)),"")
A6: Продажа | B6: Квартиры — всего | C6: Екатеринбург | D6: =SUMIFS(ЦИАН!$D:$D,ЦИАН!$A:$A,"Продажи квартир",ЦИАН!$B:$B,"Квартиры в новостройках",ЦИАН!$C:$C,$C6)+SUMIFS(ЦИАН!$D:$D,ЦИАН!$A:$A,"Продажи квартир",ЦИАН!$B:$B,"Квартиры во вторичке",ЦИАН!$C:$C,$C6) | E6: =SUMIFS(Яндекс!$D:$D,Яндекс!$A:$A,"Купить",Яндекс!$B:$B,"Квартира в новостройке",Яндекс!$C:$C,$C6)+SUMIFS(Яндекс!$D:$D,Яндекс!$A:$A,"Купить",Яндекс!$B:$B,"Квартира во вторичке",Яндекс!$C:$C,$C6) | F6: =SUMIFS(Авито!$E:$E,Авито!$A:$A,"Продажа",Авито!$B:$B,"Квартиры",Авито!$C:$C,$C6) | G6: =SUMIFS(Домклик!$D:$D,Домклик!$A:$A,"Покупка",Домклик!$B:$B,"Квартиры",Домклик!$C:$C,$C6) | H6: =IFERROR(INDEX($D$1:$G$1,MATCH(MAX(D6:G6),D6:G6,0)),"")
A7: Продажа | B7: Квартиры — всего | C7: Казань | D7: =SUMIFS(ЦИАН!$D:$D,ЦИАН!$A:$A,"Продажи квартир",ЦИАН!$B:$B,"Квартиры в новостройках",ЦИАН!$C:$C,$C7)+SUMIFS(ЦИАН!$D:$D,ЦИАН!$A:$A,"Продажи квартир",ЦИАН!$B:$B,"Квартиры во вторичке",ЦИАН!$C:$C,$C7) | E7: =SUMIFS(Яндекс!$D:$D,Яндекс!$A:$A,"Купить",Яндекс!$B:$B,"Квартира в новостройке",Яндекс!$C:$C,$C7)+SUMIFS(Яндекс!$D:$D,Яндекс!$A:$A,"Купить",Яндекс!$B:$B,"Квартира во вторичке",Яндекс!$C:$C,$C7) | F7: =SUMIFS(Авито!$E:$E,Авито!$A:$A,"Продажа",Авито!$B:$B,"Квартиры",Авито!$C:$C,$C7) | G7: =SUMIFS(Домклик!$D:$D,Домклик!$A:$A,"Покупка",Домклик!$B:$B,"Квартиры",Домклик!$C:$C,$C7) | H7: =IFERROR(INDEX($D$1:$G$1,MATCH(MAX(D7:G7),D7:G7,0)),"")
A8: Продажа | B8: Квартиры — всего | C8: Красноярск | D8: =SUMIFS(ЦИАН!$D:$D,ЦИАН!$A:$A,"Продажи квартир",ЦИАН!$B:$B,"Квартиры в новостройках",ЦИАН!$C:$C,$C8)+SUMIFS(ЦИАН!$D:$D,ЦИАН!$A:$A,"Продажи квартир",ЦИАН!$B:$B,"Квартиры во вторичке",ЦИАН!$C:$C,$C8) | E8: =SUMIFS(Яндекс!$D:$D,Яндекс!$A:$A,"Купить",Яндекс!$B:$B,"Квартира в новостройке",Яндекс!$C:$C,$C8)+SUMIFS(Яндекс!$D:$D,Яндекс!$A:$A,"Купить",Яндекс!$B:$B,"Квартира во вторичке",Яндекс!$C:$C,$C8) | F8: =SUMIFS(Авито!$E:$E,Авито!$A:$A,"Продажа",Авито!$B:$B,"Квартиры",Авито!$C:$C,$C8) | G8: =SUMIFS(Домклик!$D:$D,Домклик!$A:$A,"Покупка",Домклик!$B:$B,"Квартиры",Домклик!$C:$C,$C8) | H8: =IFERROR(INDEX($D$1:$G$1,MATCH(MAX(D8:G8),D8:G8,0)),"")
A9: Продажа | B9: Квартиры — всего | C9: Нижний Новгород | D9: =SUMIFS(ЦИАН!$D:$D,ЦИАН!$A:$A,"Продажи квартир",ЦИАН!$B:$B,"Квартиры в новостройках",ЦИАН!$C:$C,$C9)+SUMIFS(ЦИАН!$D:$D,ЦИАН!$A:$A,"Продажи квартир",ЦИАН!$B:$B,"Квартиры во вторичке",ЦИАН!$C:$C,$C9) | E9: =SUMIFS(Яндекс!$D:$D,Яндекс!$A:$A,"Купить",Яндекс!$B:$B,"Квартира в новостройке",Яндекс!$C:$C,$C9)+SUMIFS(Яндекс!$D:$D,Яндекс!$A:$A,"Купить",Яндекс!$B:$B,"Квартира во вторичке",Яндекс!$C:$C,$C9) | F9: =SUMIFS(Авито!$E:$E,Авито!$A:$A,"Продажа",Авито!$B:$B,"Квартиры",Авито!$C:$C,$C9) | G9: =SUMIFS(Домклик!$D:$D,Домклик!$A:$A,"Покупка",Домклик!$B:$B,"Квартиры",Домклик!$C:$C,$C9) | H9: =IFERROR(INDEX($D$1:$G$1,MATCH(MAX(D9:G9),D9:G9,0)),"")
A10: Продажа | B10: Квартиры — всего | C10: Челябинск | D10: =SUMIFS(ЦИАН!$D:$D,ЦИАН!$A:$A,"Продажи квартир",ЦИАН!$B:$B,"Квартиры в новостройках",ЦИАН!$C:$C,$C10)+SUMIFS(ЦИАН!$D:$D,ЦИАН!$A:$A,"Продажи квартир",ЦИАН!$B:$B,"Квартиры во вторичке",ЦИАН!$C:$C,$C10) | E10: =SUMIFS(Яндекс!$D:$D,Яндекс!$A:$A,"Купить",Яндекс!$B:$B,"Квартира в новостройке",Яндекс!$C:$C,$C10)+SUMIFS(Яндекс!$D:$D,Яндекс!$A:$A,"Купить",Яндекс!$B:$B,"Квартира во вторичке",Яндекс!$C:$C,$C10) | F10: =SUMIFS(Авито!$E:$E,Авито!$A:$A,"Продажа",Авито!$B:$B,"Квартиры",Авито!$C:$C,$C10) | G10: =SUMIFS(Домклик!$D:$D,Домклик!$A:$A,"Покупка",Домклик!$B:$B,"Квартиры",Домклик!$C:$C,$C10) | H10: =IFERROR(INDEX($D$1:$G$1,MATCH(MAX(D10:G10),D10:G10,0)),"")
A11: Продажа | B11: Квартиры — всего | C11: Уфа | D11: =SUMIFS(ЦИАН!$D:$D,ЦИАН!$A:$A,"Продажи квартир",ЦИАН!$B:$B,"Квартиры в новостройках",ЦИАН!$C:$C,$C11)+SUMIFS(ЦИАН!$D:$D,ЦИАН!$A:$A,"Продажи квартир",ЦИАН!$B:$B,"Квартиры во вторичке",ЦИАН!$C:$C,$C11) | E11: =SUMIFS(Яндекс!$D:$D,Яндекс!$A:$A,"Купить",Яндекс!$B:$B,"Квартира в новостройке",Яндекс!$C:$C,$C11)+SUMIFS(Яндекс!$D:$D,Яндекс!$A:$A,"Купить",Яндекс!$B:$B,"Квартира во вторичке",Яндекс!$C:$C,$C11) | F11: =SUMIFS(Авито!$E:$E,Авито!$A:$A,"Продажа",Авито!$B:$B,"Квартиры",Авито!$C:$C,$C11) | G11: =SUMIFS(Домклик!$D:$D,Домклик!$A:$A,"Покупка",Домклик!$B:$B,"Квартиры",Домклик!$C:$C,$C11) | H11: =IFERROR(INDEX($D$1:$G$1,MATCH(MAX(D11:G11),D11:G11,0)),"")
A12: Продажа | B12: Квартиры — всего | C12: Краснодар | D12: =SUMIFS(ЦИАН!$D:$D,ЦИАН!$A:$A,"Продажи квартир",ЦИАН!$B:$B,"Квартиры в новостройках",ЦИАН!$C:$C,$C12)+SUMIFS(ЦИАН!$D:$D,ЦИАН!$A:$A,"Продажи квартир",ЦИАН!$B:$B,"Квартиры во вторичке",ЦИАН!$C:$C,$C12) | E12: =SUMIFS(Яндекс!$D:$D,Яндекс!$A:$A,"Купить",Яндекс!$B:$B,"Квартира в новостройке",Яндекс!$C:$C,$C12)+SUMIFS(Яндекс!$D:$D,Яндекс!$A:$A,"Купить",Яндекс!$B:$B,"Квартира во вторичке",Яндекс!$C:$C,$C12) | F12: =SUMIFS(Авито!$E:$E,Авито!$A:$A,"Продажа",Авито!$B:$B,"Квартиры",Авито!$C:$C,$C12) | G12: =SUMIFS(Домклик!$D:$D,Домклик!$A:$A,"Покупка",Домклик!$B:$B,"Квартиры",Домклик!$C:$C,$C12) | H12: =IFERROR(INDEX($D$1:$G$1,MATCH(MAX(D12:G12),D12:G12,0)),"")
A13: Продажа | B13: Квартиры — всего | C13: Самара | D13: =SUMIFS(ЦИАН!$D:$D,ЦИАН!$A:$A,"Продажи квартир",ЦИАН!$B:$B,"Квартиры в новостройках",ЦИАН!$C:$C,$C13)+SUMIFS(ЦИАН!$D:$D,ЦИАН!$A:$A,"Продажи квартир",ЦИАН!$B:$B,"Квартиры во вторичке",ЦИАН!$C:$C,$C13) | E13: =SUMIFS(Яндекс!$D:$D,Яндекс!$A:$A,"Купить",Яндекс!$B:$B,"Квартира в новостройке",Яндекс!$C:$C,$C13)+SUMIFS(Яндекс!$D:$D,Яндекс!$A:$A,"Купить",Яндекс!$B:$B,"Квартира во вторичке",Яндекс!$C:$C,$C13) | F13: =SUMIFS(Авито!$E:$E,Авито!$A:$A,"Продажа",Авито!$B:$B,"Квартиры",Авито!$C:$C,$C13) | G13: =SUMIFS(Домклик!$D:$D,Домклик!$A:$A,"Покупка",Домклик!$B:$B,"Квартиры",Домклик!$C:$C,$C13) | H13: =IFERROR(INDEX($D$1:$G$1,MATCH(MAX(D13:G13),D13:G13,0)),"")
... A18: Продажа | B18: Квартиры — всего | C18: Волгоград | D18: =SUMIFS(ЦИАН!$D:$D,ЦИАН!$A:$A,"Продажи квартир",ЦИАН!$B:$B,"Квартиры в новостройках",ЦИАН!$C:$C,$C18)+SUMIFS(ЦИАН!$D:$D,ЦИАН!$A:$A,"Продажи квартир",ЦИАН!$B:$B,"Квартиры во вторичке",ЦИАН!$C:$C,$C18) | E18: =SUMIFS(Яндекс!$D:$D,Яндекс!$A:$A,"Купить",Яндекс!$B:$B,"Квартира в новостройке",Яндекс!$C:$C,$C18)+SUMIFS(Яндекс!$D:$D,Яндекс!$A:$A,"Купить",Яндекс!$B:$B,"Квартира во вторичке",Яндекс!$C:$C,$C18) | F18: =SUMIFS(Авито!$E:$E,Авито!$A:$A,"Продажа",Авито!$B:$B,"Квартиры",Авито!$C:$C,$C18) | G18: =SUMIFS(Домклик!$D:$D,Домклик!$A:$A,"Покупка",Домклик!$B:$B,"Квартиры",Домклик!$C:$C,$C18) | H18: =IFERROR(INDEX($D$1:$G$1,MATCH(MAX(D18:G18),D18:G18,0)),"")
A19: Продажа | B19: Квартиры — новостройки | C19: 🇷🇺 Вся Россия | D19: =SUMIFS(ЦИАН!$D:$D,ЦИАН!$A:$A,"Продажи квартир",ЦИАН!$B:$B,"Квартиры в новостройках",ЦИАН!$C:$C,$C19) | E19: =SUMIFS(Яндекс!$D:$D,Яндекс!$A:$A,"Купить",Яндекс!$B:$B,"Квартира в новостройке",Яндекс!$C:$C,$C19) | F19: =SUMIFS(Авито!$E:$E,Авито!$A:$A,"Продажа",Авито!$B:$B,"Квартиры новостройка",Авито!$C:$C,$C19) | G19: =SUMIFS(Домклик!$D:$D,Домклик!$A:$A,"Покупка",Домклик!$B:$B,"Квартиры новостройки",Домклик!$C:$C,$C19) | H19: =IFERROR(INDEX($D$1:$G$1,MATCH(MAX(D19:G19),D19:G19,0)),"")
A20: Продажа | B20: Квартиры — новостройки | C20: Москва | D20: =SUMIFS(ЦИАН!$D:$D,ЦИАН!$A:$A,"Продажи квартир",ЦИАН!$B:$B,"Квартиры в новостройках",ЦИАН!$C:$C,$C20) | E20: =SUMIFS(Яндекс!$D:$D,Яндекс!$A:$A,"Купить",Яндекс!$B:$B,"Квартира в новостройке",Яндекс!$C:$C,$C20) | F20: =SUMIFS(Авито!$E:$E,Авито!$A:$A,"Продажа",Авито!$B:$B,"Квартиры новостройка",Авито!$C:$C,$C20) | G20: =SUMIFS(Домклик!$D:$D,Домклик!$A:$A,"Покупка",Домклик!$B:$B,"Квартиры новостройки",Домклик!$C:$C,$C20) | H20: =IFERROR(INDEX($D$1:$G$1,MATCH(MAX(D20:G20),D20:G20,0)),"")
A21: Продажа | B21: Квартиры — новостройки | C21: Санкт-Петербург | D21: =SUMIFS(ЦИАН!$D:$D,ЦИАН!$A:$A,"Продажи квартир",ЦИАН!$B:$B,"Квартиры в новостройках",ЦИАН!$C:$C,$C21) | E21: =SUMIFS(Яндекс!$D:$D,Яндекс!$A:$A,"Купить",Яндекс!$B:$B,"Квартира в новостройке",Яндекс!$C:$C,$C21) | F21: =SUMIFS(Авито!$E:$E,Авито!$A:$A,"Продажа",Авито!$B:$B,"Квартиры новостройка",Авито!$C:$C,$C21) | G21: =SUMIFS(Домклик!$D:$D,Домклик!$A:$A,"Покупка",Домклик!$B:$B,"Квартиры новостройки",Домклик!$C:$C,$C21) | H21: =IFERROR(INDEX($D$1:$G$1,MATCH(MAX(D21:G21),D21:G21,0)),"")
A22: Продажа | B22: Квартиры — новостройки | C22: Новосибирск | D22: =SUMIFS(ЦИАН!$D:$D,ЦИАН!$A:$A,"Продажи квартир",ЦИАН!$B:$B,"Квартиры в новостройках",ЦИАН!$C:$C,$C22) | E22: =SUMIFS(Яндекс!$D:$D,Яндекс!$A:$A,"Купить",Яндекс!$B:$B,"Квартира в новостройке",Яндекс!$C:$C,$C22) | F22: =SUMIFS(Авито!$E:$E,Авито!$A:$A,"Продажа",Авито!$B:$B,"Квартиры новостройка",Авито!$C:$C,$C22) | G22: =SUMIFS(Домклик!$D:$D,Домклик!$A:$A,"Покупка",Домклик!$B:$B,"Квартиры новостройки",Домклик!$C:$C,$C22) | H22: =IFERROR(INDEX($D$1:$G$1,MATCH(MAX(D22:G22),D22:G22,0)),"")
A23: Продажа | B23: Квартиры — новостройки | C23: Екатеринбург | D23: =SUMIFS(ЦИАН!$D:$D,ЦИАН!$A:$A,"Продажи квартир",ЦИАН!$B:$B,"Квартиры в новостройках",ЦИАН!$C:$C,$C23) | E23: =SUMIFS(Яндекс!$D:$D,Яндекс!$A:$A,"Купить",Яндекс!$B:$B,"Квартира в новостройке",Яндекс!$C:$C,$C23) | F23: =SUMIFS(Авито!$E:$E,Авито!$A:$A,"Продажа",Авито!$B:$B,"Квартиры новостройка",Авито!$C:$C,$C23) | G23: =SUMIFS(Домклик!$D:$D,Домклик!$A:$A,"Покупка",Домклик!$B:$B,"Квартиры новостройки",Домклик!$C:$C,$C23) | H23: =IFERROR(INDEX($D$1:$G$1,MATCH(MAX(D23:G23),D23:G23,0)),"")
A24: Продажа | B24: Квартиры — новостройки | C24: Казань | D24: =SUMIFS(ЦИАН!$D:$D,ЦИАН!$A:$A,"Продажи квартир",ЦИАН!$B:$B,"Квартиры в новостройках",ЦИАН!$C:$C,$C24) | E24: =SUMIFS(Яндекс!$D:$D,Яндекс!$A:$A,"Купить",Яндекс!$B:$B,"Квартира в новостройке",Яндекс!$C:$C,$C24) | F24: =SUMIFS(Авито!$E:$E,Авито!$A:$A,"Продажа",Авито!$B:$B,"Квартиры новостройка",Авито!$C:$C,$C24) | G24: =SUMIFS(Домклик!$D:$D,Домклик!$A:$A,"Покупка",Домклик!$B:$B,"Квартиры новостройки",Домклик!$C:$C,$C24) | H24: =IFERROR(INDEX($D$1:$G$1,MATCH(MAX(D24:G24),D24:G24,0)),"")
A25: Продажа | B25: Квартиры — новостройки | C25: Красноярск | D25: =SUMIFS(ЦИАН!$D:$D,ЦИАН!$A:$A,"Продажи квартир",ЦИАН!$B:$B,"Квартиры в новостройках",ЦИАН!$C:$C,$C25) | E25: =SUMIFS(Яндекс!$D:$D,Яндекс!$A:$A,"Купить",Яндекс!$B:$B,"Квартира в новостройке",Яндекс!$C:$C,$C25) | F25: =SUMIFS(Авито!$E:$E,Авито!$A:$A,"Продажа",Авито!$B:$B,"Квартиры новостройка",Авито!$C:$C,$C25) | G25: =SUMIFS(Домклик!$D:$D,Домклик!$A:$A,"Покупка",Домклик!$B:$B,"Квартиры новостройки",Домклик!$C:$C,$C25) | H25: =IFERROR(INDEX($D$1:$G$1,MATCH(MAX(D25:G25),D25:G25,0)),"")
A26: Продажа | B26: Квартиры — новостройки | C26: Нижний Новгород | D26: =SUMIFS(ЦИАН!$D:$D,ЦИАН!$A:$A,"Продажи квартир",ЦИАН!$B:$B,"Квартиры в новостройках",ЦИАН!$C:$C,$C26) | E26: =SUMIFS(Яндекс!$D:$D,Яндекс!$A:$A,"Купить",Яндекс!$B:$B,"Квартира в новостройке",Яндекс!$C:$C,$C26) | F26: =SUMIFS(Авито!$E:$E,Авито!$A:$A,"Продажа",Авито!$B:$B,"Квартиры новостройка",Авито!$C:$C,$C26) | G26: =SUMIFS(Домклик!$D:$D,Домклик!$A:$A,"Покупка",Домклик!$B:$B,"Квартиры новостройки",Домклик!$C:$C,$C26) | H26: =IFERROR(INDEX($D$1:$G$1,MATCH(MAX(D26:G26),D26:G26,0)),"")
A27: Продажа | B27: Квартиры — новостройки | C27: Челябинск | D27: =SUMIFS(ЦИАН!$D:$D,ЦИАН!$A:$A,"Продажи квартир",ЦИАН!$B:$B,"Квартиры в новостройках",ЦИАН!$C:$C,$C27) | E27: =SUMIFS(Яндекс!$D:$D,Яндекс!$A:$A,"Купить",Яндекс!$B:$B,"Квартира в новостройке",Яндекс!$C:$C,$C27) | F27: =SUMIFS(Авито!$E:$E,Авито!$A:$A,"Продажа",Авито!$B:$B,"Квартиры новостройка",Авито!$C:$C,$C27) | G27: =SUMIFS(Домклик!$D:$D,Домклик!$A:$A,"Покупка",Домклик!$B:$B,"Квартиры новостройки",Домклик!$C:$C,$C27) | H27: =IFERROR(INDEX($D$1:$G$1,MATCH(MAX(D27:G27),D27:G27,0)),"")
A28: Продажа | B28: Квартиры — новостройки | C28: Уфа | D28: =SUMIFS(ЦИАН!$D:$D,ЦИАН!$A:$A,"Продажи квартир",ЦИАН!$B:$B,"Квартиры в новостройках",ЦИАН!$C:$C,$C28) | E28: =SUMIFS(Яндекс!$D:$D,Яндекс!$A:$A,"Купить",Яндекс!$B:$B,"Квартира в новостройке",Яндекс!$C:$C,$C28) | F28: =SUMIFS(Авито!$E:$E,Авито!$A:$A,"Продажа",Авито!$B:$B,"Квартиры новостройка",Авито!$C:$C,$C28) | G28: =SUMIFS(Домклик!$D:$D,Домклик!$A:$A,"Покупка",Домклик!$B:$B,"Квартиры новостройки",Домклик!$C:$C,$C28) | H28: =IFERROR(INDEX($D$1:$G$1,MATCH(MAX(D28:G28),D28:G28,0)),"")
A29: Продажа | B29: Квартиры — новостройки | C29: Краснодар | D29: =SUMIFS(ЦИАН!$D:$D,ЦИАН!$A:$A,"Продажи квартир",ЦИАН!$B:$B,"Квартиры в новостройках",ЦИАН!$C:$C,$C29) | E29: =SUMIFS(Яндекс!$D:$D,Яндекс!$A:$A,"Купить",Яндекс!$B:$B,"Квартира в новостройке",Яндекс!$C:$C,$C29) | F29: =SUMIFS(Авито!$E:$E,Авито!$A:$A,"Продажа",Авито!$B:$B,"Квартиры новостройка",Авито!$C:$C,$C29) | G29: =SUMIFS(Домклик!$D:$D,Домклик!$A:$A,"Покупка",Домклик!$B:$B,"Квартиры новостройки",Домклик!$C:$C,$C29) | H29: =IFERROR(INDEX($D$1:$G$1,MATCH(MAX(D29:G29),D29:G29,0)),"")
A30: Продажа | B30: Квартиры — новостройки | C30: Самара | D30: =SUMIFS(ЦИАН!$D:$D,ЦИАН!$A:$A,"Продажи квартир",ЦИАН!$B:$B,"Квартиры в новостройках",ЦИАН!$C:$C,$C30) | E30: =SUMIFS(Яндекс!$D:$D,Яндекс!$A:$A,"Купить",Яндекс!$B:$B,"Квартира в новостройке",Яндекс!$C:$C,$C30) | F30: =SUMIFS(Авито!$E:$E,Авито!$A:$A,"Продажа",Авито!$B:$B,"Квартиры новостройка",Авито!$C:$C,$C30) | G30: =SUMIFS(Домклик!$D:$D,Домклик!$A:$A,"Покупка",Домклик!$B:$B,"Квартиры новостройки",Домклик!$C:$C,$C30) | H30: =IFERROR(INDEX($D$1:$G$1,MATCH(MAX(D30:G30),D30:G30,0)),"")
... A35: Продажа | B35: Квартиры — новостройки | C35: Волгоград | D35: =SUMIFS(ЦИАН!$D:$D,ЦИАН!$A:$A,"Продажи квартир",ЦИАН!$B:$B,"Квартиры в новостройках",ЦИАН!$C:$C,$C35) | E35: =SUMIFS(Яндекс!$D:$D,Яндекс!$A:$A,"Купить",Яндекс!$B:$B,"Квартира в новостройке",Яндекс!$C:$C,$C35) | F35: =SUMIFS(Авито!$E:$E,Авито!$A:$A,"Продажа",Авито!$B:$B,"Квартиры новостройка",Авито!$C:$C,$C35) | G35: =SUMIFS(Домклик!$D:$D,Домклик!$A:$A,"Покупка",Домклик!$B:$B,"Квартиры новостройки",Домклик!$C:$C,$C35) | H35: =IFERROR(INDEX($D$1:$G$1,MATCH(MAX(D35:G35),D35:G35,0)),"")
A36: Продажа | B36: Квартиры — вторичка | C36: 🇷🇺 Вся Россия | D36: =SUMIFS(ЦИАН!$D:$D,ЦИАН!$A:$A,"Продажи квартир",ЦИАН!$B:$B,"Квартиры во вторичке",ЦИАН!$C:$C,$C36) | E36: =SUMIFS(Яндекс!$D:$D,Яндекс!$A:$A,"Купить",Яндекс!$B:$B,"Квартира во вторичке",Яндекс!$C:$C,$C36) | F36: =SUMIFS(Авито!$E:$E,Авито!$A:$A,"Продажа",Авито!$B:$B,"Квартиры вторичка",Авито!$C:$C,$C36) | G36: =SUMIFS(Домклик!$D:$D,Домклик!$A:$A,"Покупка",Домклик!$B:$B,"Квартиры вторичка",Домклик!$C:$C,$C36) | H36: =IFERROR(INDEX($D$1:$G$1,MATCH(MAX(D36:G36),D36:G36,0)),"")
A37: Продажа | B37: Квартиры — вторичка | C37: Москва | D37: =SUMIFS(ЦИАН!$D:$D,ЦИАН!$A:$A,"Продажи квартир",ЦИАН!$B:$B,"Квартиры во вторичке",ЦИАН!$C:$C,$C37) | E37: =SUMIFS(Яндекс!$D:$D,Яндекс!$A:$A,"Купить",Яндекс!$B:$B,"Квартира во вторичке",Яндекс!$C:$C,$C37) | F37: =SUMIFS(Авито!$E:$E,Авито!$A:$A,"Продажа",Авито!$B:$B,"Квартиры вторичка",Авито!$C:$C,$C37) | G37: =SUMIFS(Домклик!$D:$D,Домклик!$A:$A,"Покупка",Домклик!$B:$B,"Квартиры вторичка",Домклик!$C:$C,$C37) | H37: =IFERROR(INDEX($D$1:$G$1,MATCH(MAX(D37:G37),D37:G37,0)),"")
A38: Продажа | B38: Квартиры — вторичка | C38: Санкт-Петербург | D38: =SUMIFS(ЦИАН!$D:$D,ЦИАН!$A:$A,"Продажи квартир",ЦИАН!$B:$B,"Квартиры во вторичке",ЦИАН!$C:$C,$C38) | E38: =SUMIFS(Яндекс!$D:$D,Яндекс!$A:$A,"Купить",Яндекс!$B:$B,"Квартира во вторичке",Яндекс!$C:$C,$C38) | F38: =SUMIFS(Авито!$E:$E,Авито!$A:$A,"Продажа",Авито!$B:$B,"Квартиры вторичка",Авито!$C:$C,$C38) | G38: =SUMIFS(Домклик!$D:$D,Домклик!$A:$A,"Покупка",Домклик!$B:$B,"Квартиры вторичка",Домклик!$C:$C,$C38) | H38: =IFERROR(INDEX($D$1:$G$1,MATCH(MAX(D38:G38),D38:G38,0)),"")
A39: Продажа | B39: Квартиры — вторичка | C39: Новосибирск | D39: =SUMIFS(ЦИАН!$D:$D,ЦИАН!$A:$A,"Продажи квартир",ЦИАН!$B:$B,"Квартиры во вторичке",ЦИАН!$C:$C,$C39) | E39: =SUMIFS(Яндекс!$D:$D,Яндекс!$A:$A,"Купить",Яндекс!$B:$B,"Квартира во вторичке",Яндекс!$C:$C,$C39) | F39: =SUMIFS(Авито!$E:$E,Авито!$A:$A,"Продажа",Авито!$B:$B,"Квартиры вторичка",Авито!$C:$C,$C39) | G39: =SUMIFS(Домклик!$D:$D,Домклик!$A:$A,"Покупка",Домклик!$B:$B,"Квартиры вторичка",Домклик!$C:$C,$C39) | H39: =IFERROR(INDEX($D$1:$G$1,MATCH(MAX(D39:G39),D39:G39,0)),"")
A40: Продажа | B40: Квартиры — вторичка | C40: Екатеринбург | D40: =SUMIFS(ЦИАН!$D:$D,ЦИАН!$A:$A,"Продажи квартир",ЦИАН!$B:$B,"Квартиры во вторичке",ЦИАН!$C:$C,$C40) | E40: =SUMIFS(Яндекс!$D:$D,Яндекс!$A:$A,"Купить",Яндекс!$B:$B,"Квартира во вторичке",Яндекс!$C:$C,$C40) | F40: =SUMIFS(Авито!$E:$E,Авито!$A:$A,"Продажа",Авито!$B:$B,"Квартиры вторичка",Авито!$C:$C,$C40) | G40: =SUMIFS(Домклик!$D:$D,Домклик!$A:$A,"Покупка",Домклик!$B:$B,"Квартиры вторичка",Домклик!$C:$C,$C40) | H40: =IFERROR(INDEX($D$1:$G$1,MATCH(MAX(D40:G40),D40:G40,0)),"")
A41: Продажа | B41: Квартиры — вторичка | C41: Казань | D41: =SUMIFS(ЦИАН!$D:$D,ЦИАН!$A:$A,"Продажи квартир",ЦИАН!$B:$B,"Квартиры во вторичке",ЦИАН!$C:$C,$C41) | E41: =SUMIFS(Яндекс!$D:$D,Яндекс!$A:$A,"Купить",Яндекс!$B:$B,"Квартира во вторичке",Яндекс!$C:$C,$C41) | F41: =SUMIFS(Авито!$E:$E,Авито!$A:$A,"Продажа",Авито!$B:$B,"Квартиры вторичка",Авито!$C:$C,$C41) | G41: =SUMIFS(Домклик!$D:$D,Домклик!$A:$A,"Покупка",Домклик!$B:$B,"Квартиры вторичка",Домклик!$C:$C,$C41) | H41: =IFERROR(INDEX($D$1:$G$1,MATCH(MAX(D41:G41),D41:G41,0)),"")
A42: Продажа | B42: Квартиры — вторичка | C42: Красноярск | D42: =SUMIFS(ЦИАН!$D:$D,ЦИАН!$A:$A,"Продажи квартир",ЦИАН!$B:$B,"Квартиры во вторичке",ЦИАН!$C:$C,$C42) | E42: =SUMIFS(Яндекс!$D:$D,Яндекс!$A:$A,"Купить",Яндекс!$B:$B,"Квартира во вторичке",Яндекс!$C:$C,$C42) | F42: =SUMIFS(Авито!$E:$E,Авито!$A:$A,"Продажа",Авито!$B:$B,"Квартиры вторичка",Авито!$C:$C,$C42) | G42: =SUMIFS(Домклик!$D:$D,Домклик!$A:$A,"Покупка",Домклик!$B:$B,"Квартиры вторичка",Домклик!$C:$C,$C42) | H42: =IFERROR(INDEX($D$1:$G$1,MATCH(MAX(D42:G42),D42:G42,0)),"")
A43: Продажа | B43: Квартиры — вторичка | C43: Нижний Новгород | D43: =SUMIFS(ЦИАН!$D:$D,ЦИАН!$A:$A,"Продажи квартир",ЦИАН!$B:$B,"Квартиры во вторичке",ЦИАН!$C:$C,$C43) | E43: =SUMIFS(Яндекс!$D:$D,Яндекс!$A:$A,"Купить",Яндекс!$B:$B,"Квартира во вторичке",Яндекс!$C:$C,$C43) | F43: =SUMIFS(Авито!$E:$E,Авито!$A:$A,"Продажа",Авито!$B:$B,"Квартиры вторичка",Авито!$C:$C,$C43) | G43: =SUMIFS(Домклик!$D:$D,Домклик!$A:$A,"Покупка",Домклик!$B:$B,"Квартиры вторичка",Домклик!$C:$C,$C43) | H43: =IFERROR(INDEX($D$1:$G$1,MATCH(MAX(D43:G43),D43:G43,0)),"")
A44: Продажа | B44: Квартиры — вторичка | C44: Челябинск | D44: =SUMIFS(ЦИАН!$D:$D,ЦИАН!$A:$A,"Продажи квартир",ЦИАН!$B:$B,"Квартиры во вторичке",ЦИАН!$C:$C,$C44) | E44: =SUMIFS(Яндекс!$D:$D,Яндекс!$A:$A,"Купить",Яндекс!$B:$B,"Квартира во вторичке",Яндекс!$C:$C,$C44) | F44: =SUMIFS(Авито!$E:$E,Авито!$A:$A,"Продажа",Авито!$B:$B,"Квартиры вторичка",Авито!$C:$C,$C44) | G44: =SUMIFS(Домклик!$D:$D,Домклик!$A:$A,"Покупка",Домклик!$B:$B,"Квартиры вторичка",Домклик!$C:$C,$C44) | H44: =IFERROR(INDEX($D$1:$G$1,MATCH(MAX(D44:G44),D44:G44,0)),"")
A45: Продажа | B45: Квартиры — вторичка | C45: Уфа | D45: =SUMIFS(ЦИАН!$D:$D,ЦИАН!$A:$A,"Продажи квартир",ЦИАН!$B:$B,"Квартиры во вторичке",ЦИАН!$C:$C,$C45) | E45: =SUMIFS(Яндекс!$D:$D,Яндекс!$A:$A,"Купить",Яндекс!$B:$B,"Квартира во вторичке",Яндекс!$C:$C,$C45) | F45: =SUMIFS(Авито!$E:$E,Авито!$A:$A,"Продажа",Авито!$B:$B,"Квартиры вторичка",Авито!$C:$C,$C45) | G45: =SUMIFS(Домклик!$D:$D,Домклик!$A:$A,"Покупка",Домклик!$B:$B,"Квартиры вторичка",Домклик!$C:$C,$C45) | H45: =IFERROR(INDEX($D$1:$G$1,MATCH(MAX(D45:G45),D45:G45,0)),"")
A46: Продажа | B46: Квартиры — вторичка | C46: Краснодар | D46: =SUMIFS(ЦИАН!$D:$D,ЦИАН!$A:$A,"Продажи квартир",ЦИАН!$B:$B,"Квартиры во вторичке",ЦИАН!$C:$C,$C46) | E46: =SUMIFS(Яндекс!$D:$D,Яндекс!$A:$A,"Купить",Яндекс!$B:$B,"Квартира во вторичке",Яндекс!$C:$C,$C46) | F46: =SUMIFS(Авито!$E:$E,Авито!$A:$A,"Продажа",Авито!$B:$B,"Квартиры вторичка",Авито!$C:$C,$C46) | G46: =SUMIFS(Домклик!$D:$D,Домклик!$A:$A,"Покупка",Домклик!$B:$B,"Квартиры вторичка",Домклик!$C:$C,$C46) | H46: =IFERROR(INDEX($D$1:$G$1,MATCH(MAX(D46:G46),D46:G46,0)),"")
A47: Продажа | B47: Квартиры — вторичка | C47: Самара | D47: =SUMIFS(ЦИАН!$D:$D,ЦИАН!$A:$A,"Продажи квартир",ЦИАН!$B:$B,"Квартиры во вторичке",ЦИАН!$C:$C,$C47) | E47: =SUMIFS(Яндекс!$D:$D,Яндекс!$A:$A,"Купить",Яндекс!$B:$B,"Квартира во вторичке",Яндекс!$C:$C,$C47) | F47: =SUMIFS(Авито!$E:$E,Авито!$A:$A,"Продажа",Авито!$B:$B,"Квартиры вторичка",Авито!$C:$C,$C47) | G47: =SUMIFS(Домклик!$D:$D,Домклик!$A:$A,"Покупка",Домклик!$B:$B,"Квартиры вторичка",Домклик!$C:$C,$C47) | H47: =IFERROR(INDEX($D$1:$G$1,MATCH(MAX(D47:G47),D47:G47,0)),"")
... A52: Продажа | B52: Квартиры — вторичка | C52: Волгоград | D52: =SUMIFS(ЦИАН!$D:$D,ЦИАН!$A:$A,"Продажи квартир",ЦИАН!$B:$B,"Квартиры во вторичке",ЦИАН!$C:$C,$C52) | E52: =SUMIFS(Яндекс!$D:$D,Яндекс!$A:$A,"Купить",Яндекс!$B:$B,"Квартира во вторичке",Яндекс!$C:$C,$C52) | F52: =SUMIFS(Авито!$E:$E,Авито!$A:$A,"Продажа",Авито!$B:$B,"Квартиры вторичка",Авито!$C:$C,$C52) | G52: =SUMIFS(Домклик!$D:$D,Домклик!$A:$A,"Покупка",Домклик!$B:$B,"Квартиры вторичка",Домклик!$C:$C,$C52) | H52: =IFERROR(INDEX($D$1:$G$1,MATCH(MAX(D52:G52),D52:G52,0)),"")
A53: Продажа | B53: Комнаты | C53: 🇷🇺 Вся Россия | D53: =SUMIFS(ЦИАН!$D:$D,ЦИАН!$A:$A,"Продажи квартир",ЦИАН!$B:$B,"Комнаты",ЦИАН!$C:$C,$C53) | E53: =SUMIFS(Яндекс!$D:$D,Яндекс!$A:$A,"Купить",Яндекс!$B:$B,"Комната",Яндекс!$C:$C,$C53) | F53: =SUMIFS(Авито!$E:$E,Авито!$A:$A,"Продажа",Авито!$B:$B,"Комнаты",Авито!$C:$C,$C53) | G53: =SUMIFS(Домклик!$D:$D,Домклик!$A:$A,"Покупка",Домклик!$B:$B,"Комнаты",Домклик!$C:$C,$C53) | H53: =IFERROR(INDEX($D$1:$G$1,MATCH(MAX(D53:G53),D53:G53,0)),"")
A54: Продажа | B54: Комнаты | C54: Москва | D54: =SUMIFS(ЦИАН!$D:$D,ЦИАН!$A:$A,"Продажи квартир",ЦИАН!$B:$B,"Комнаты",ЦИАН!$C:$C,$C54) | E54: =SUMIFS(Яндекс!$D:$D,Яндекс!$A:$A,"Купить",Яндекс!$B:$B,"Комната",Яндекс!$C:$C,$C54) | F54: =SUMIFS(Авито!$E:$E,Авито!$A:$A,"Продажа",Авито!$B:$B,"Комнаты",Авито!$C:$C,$C54) | G54: =SUMIFS(Домклик!$D:$D,Домклик!$A:$A,"Покупка",Домклик!$B:$B,"Комнаты",Домклик!$C:$C,$C54) | H54: =IFERROR(INDEX($D$1:$G$1,MATCH(MAX(D54:G54),D54:G54,0)),"")
A55: Продажа | B55: Комнаты | C55: Санкт-Петербург | D55: =SUMIFS(ЦИАН!$D:$D,ЦИАН!$A:$A,"Продажи квартир",ЦИАН!$B:$B,"Комнаты",ЦИАН!$C:$C,$C55) | E55: =SUMIFS(Яндекс!$D:$D,Яндекс!$A:$A,"Купить",Яндекс!$B:$B,"Комната",Яндекс!$C:$C,$C55) | F55: =SUMIFS(Авито!$E:$E,Авито!$A:$A,"Продажа",Авито!$B:$B,"Комнаты",Авито!$C:$C,$C55) | G55: =SUMIFS(Домклик!$D:$D,Домклик!$A:$A,"Покупка",Домклик!$B:$B,"Комнаты",Домклик!$C:$C,$C55) | H55: =IFERROR(INDEX($D$1:$G$1,MATCH(MAX(D55:G55),D55:G55,0)),"")
A56: Продажа | B56: Комнаты | C56: Новосибирск | D56: =SUMIFS(ЦИАН!$D:$D,ЦИАН!$A:$A,"Продажи квартир",ЦИАН!$B:$B,"Комнаты",ЦИАН!$C:$C,$C56) | E56: =SUMIFS(Яндекс!$D:$D,Яндекс!$A:$A,"Купить",Яндекс!$B:$B,"Комната",Яндекс!$C:$C,$C56) | F56: =SUMIFS(Авито!$E:$E,Авито!$A:$A,"Продажа",Авито!$B:$B,"Комнаты",Авито!$C:$C,$C56) | G56: =SUMIFS(Домклик!$D:$D,Домклик!$A:$A,"Покупка",Домклик!$B:$B,"Комнаты",Домклик!$C:$C,$C56) | H56: =IFERROR(INDEX($D$1:$G$1,MATCH(MAX(D56:G56),D56:G56,0)),"")
A57: Продажа | B57: Комнаты | C57: Екатеринбург | D57: =SUMIFS(ЦИАН!$D:$D,ЦИАН!$A:$A,"Продажи квартир",ЦИАН!$B:$B,"Комнаты",ЦИАН!$C:$C,$C57) | E57: =SUMIFS(Яндекс!$D:$D,Яндекс!$A:$A,"Купить",Яндекс!$B:$B,"Комната",Яндекс!$C:$C,$C57) | F57: =SUMIFS(Авито!$E:$E,Авито!$A:$A,"Продажа",Авито!$B:$B,"Комнаты",Авито!$C:$C,$C57) | G57: =SUMIFS(Домклик!$D:$D,Домклик!$A:$A,"Покупка",Домклик!$B:$B,"Комнаты",Домклик!$C:$C,$C57) | H57: =IFERROR(INDEX($D$1:$G$1,MATCH(MAX(D57:G57),D57:G57,0)),"")
A58: Продажа | B58: Комнаты | C58: Казань | D58: =SUMIFS(ЦИАН!$D:$D,ЦИАН!$A:$A,"Продажи квартир",ЦИАН!$B:$B,"Комнаты",ЦИАН!$C:$C,$C58) | E58: =SUMIFS(Яндекс!$D:$D,Яндекс!$A:$A,"Купить",Яндекс!$B:$B,"Комната",Яндекс!$C:$C,$C58) | F58: =SUMIFS(Авито!$E:$E,Авито!$A:$A,"Продажа",Авито!$B:$B,"Комнаты",Авито!$C:$C,$C58) | G58: =SUMIFS(Домклик!$D:$D,Домклик!$A:$A,"Покупка",Домклик!$B:$B,"Комнаты",Домклик!$C:$C,$C58) | H58: =IFERROR(INDEX($D$1:$G$1,MATCH(MAX(D58:G58),D58:G58,0)),"")
A59: Продажа | B59: Комнаты | C59: Красноярск | D59: =SUMIFS(ЦИАН!$D:$D,ЦИАН!$A:$A,"Продажи квартир",ЦИАН!$B:$B,"Комнаты",ЦИАН!$C:$C,$C59) | E59: =SUMIFS(Яндекс!$D:$D,Яндекс!$A:$A,"Купить",Яндекс!$B:$B,"Комната",Яндекс!$C:$C,$C59) | F59: =SUMIFS(Авито!$E:$E,Авито!$A:$A,"Продажа",Авито!$B:$B,"Комнаты",Авито!$C:$C,$C59) | G59: =SUMIFS(Домклик!$D:$D,Домклик!$A:$A,"Покупка",Домклик!$B:$B,"Комнаты",Домклик!$C:$C,$C59) | H59: =IFERROR(INDEX($D$1:$G$1,MATCH(MAX(D59:G59),D59:G59,0)),"")
A60: Продажа | B60: Комнаты | C60: Нижний Новгород | D60: =SUMIFS(ЦИАН!$D:$D,ЦИАН!$A:$A,"Продажи квартир",ЦИАН!$B:$B,"Комнаты",ЦИАН!$C:$C,$C60) | E60: =SUMIFS(Яндекс!$D:$D,Яндекс!$A:$A,"Купить",Яндекс!$B:$B,"Комната",Яндекс!$C:$C,$C60) | F60: =SUMIFS(Авито!$E:$E,Авито!$A:$A,"Продажа",Авито!$B:$B,"Комнаты",Авито!$C:$C,$C60) | G60: =SUMIFS(Домклик!$D:$D,Домклик!$A:$A,"Покупка",Домклик!$B:$B,"Комнаты",Домклик!$C:$C,$C60) | H60: =IFERROR(INDEX($D$1:$G$1,MATCH(MAX(D60:G60),D60:G60,0)),"")
A61: Продажа | B61: Комнаты | C61: Челябинск | D61: =SUMIFS(ЦИАН!$D:$D,ЦИАН!$A:$A,"Продажи квартир",ЦИАН!$B:$B,"Комнаты",ЦИАН!$C:$C,$C61) | E61: =SUMIFS(Яндекс!$D:$D,Яндекс!$A:$A,"Купить",Яндекс!$B:$B,"Комната",Яндекс!$C:$C,$C61) | F61: =SUMIFS(Авито!$E:$E,Авито!$A:$A,"Продажа",Авито!$B:$B,"Комнаты",Авито!$C:$C,$C61) | G61: =SUMIFS(Домклик!$D:$D,Домклик!$A:$A,"Покупка",Домклик!$B:$B,"Комнаты",Домклик!$C:$C,$C61) | H61: =IFERROR(INDEX($D$1:$G$1,MATCH(MAX(D61:G61),D61:G61,0)),"")
A62: Продажа | B62: Комнаты | C62: Уфа | D62: =SUMIFS(ЦИАН!$D:$D,ЦИАН!$A:$A,"Продажи квартир",ЦИАН!$B:$B,"Комнаты",ЦИАН!$C:$C,$C62) | E62: =SUMIFS(Яндекс!$D:$D,Яндекс!$A:$A,"Купить",Яндекс!$B:$B,"Комната",Яндекс!$C:$C,$C62) | F62: =SUMIFS(Авито!$E:$E,Авито!$A:$A,"Продажа",Авито!$B:$B,"Комнаты",Авито!$C:$C,$C62) | G62: =SUMIFS(Домклик!$D:$D,Домклик!$A:$A,"Покупка",Домклик!$B:$B,"Комнаты",Домклик!$C:$C,$C62) | H62: =IFERROR(INDEX($D$1:$G$1,MATCH(MAX(D62:G62),D62:G62,0)),"")
A63: Продажа | B63: Комнаты | C63: Краснодар | D63: =SUMIFS(ЦИАН!$D:$D,ЦИАН!$A:$A,"Продажи квартир",ЦИАН!$B:$B,"Комнаты",ЦИАН!$C:$C,$C63) | E63: =SUMIFS(Яндекс!$D:$D,Яндекс!$A:$A,"Купить",Яндекс!$B:$B,"Комната",Яндекс!$C:$C,$C63) | F63: =SUMIFS(Авито!$E:$E,Авито!$A:$A,"Продажа",Авито!$B:$B,"Комнаты",Авито!$C:$C,$C63) | G63: =SUMIFS(Домклик!$D:$D,Домклик!$A:$A,"Покупка",Домклик!$B:$B,"Комнаты",Домклик!$C:$C,$C63) | H63: =IFERROR(INDEX($D$1:$G$1,MATCH(MAX(D63:G63),D63:G63,0)),"")
A64: Продажа | B64: Комнаты | C64: Самара | D64: =SUMIFS(ЦИАН!$D:$D,ЦИАН!$A:$A,"Продажи квартир",ЦИАН!$B:$B,"Комнаты",ЦИАН!$C:$C,$C64) | E64: =SUMIFS(Яндекс!$D:$D,Яндекс!$A:$A,"Купить",Яндекс!$B:$B,"Комната",Яндекс!$C:$C,$C64) | F64: =SUMIFS(Авито!$E:$E,Авито!$A:$A,"Продажа",Авито!$B:$B,"Комнаты",Авито!$C:$C,$C64) | G64: =SUMIFS(Домклик!$D:$D,Домклик!$A:$A,"Покупка",Домклик!$B:$B,"Комнаты",Домклик!$C:$C,$C64) | H64: =IFERROR(INDEX($D$1:$G$1,MATCH(MAX(D64:G64),D64:G64,0)),"")
... A69: Продажа | B69: Комнаты | C69: Волгоград | D69: =SUMIFS(ЦИАН!$D:$D,ЦИАН!$A:$A,"Продажи квартир",ЦИАН!$B:$B,"Комнаты",ЦИАН!$C:$C,$C69) | E69: =SUMIFS(Яндекс!$D:$D,Яндекс!$A:$A,"Купить",Яндекс!$B:$B,"Комната",Яндекс!$C:$C,$C69) | F69: =SUMIFS(Авито!$E:$E,Авито!$A:$A,"Продажа",Авито!$B:$B,"Комнаты",Авито!$C:$C,$C69) | G69: =SUMIFS(Домклик!$D:$D,Домклик!$A:$A,"Покупка",Домклик!$B:$B,"Комнаты",Домклик!$C:$C,$C69) | H69: =IFERROR(INDEX($D$1:$G$1,MATCH(MAX(D69:G69),D69:G69,0)),"")
A70: Продажа | B70: Дома и коттеджи | C70: 🇷🇺 Вся Россия | D70: =SUMIFS(ЦИАН!$D:$D,ЦИАН!$A:$A,"Продажи квартир",ЦИАН!$B:$B,"Дома и коттеджи",ЦИАН!$C:$C,$C70) | E70: =SUMIFS(Яндекс!$D:$D,Яндекс!$A:$A,"Купить",Яндекс!$B:$B,"Дом или коттедж",Яндекс!$C:$C,$C70) | F70: =SUMIFS(Авито!$E:$E,Авито!$A:$A,"Продажа",Авито!$B:$B,"Дома, дачи, коттеджи",Авито!$C:$C,$C70) | G70: =SUMIFS(Домклик!$D:$D,Домклик!$A:$A,"Покупка",Домклик!$B:$B,"Дом",Домклик!$C:$C,$C70) | H70: =IFERROR(INDEX($D$1:$G$1,MATCH(MAX(D70:G70),D70:G70,0)),"")
A71: Продажа | B71: Дома и коттеджи | C71: Москва | D71: =SUMIFS(ЦИАН!$D:$D,ЦИАН!$A:$A,"Продажи квартир",ЦИАН!$B:$B,"Дома и коттеджи",ЦИАН!$C:$C,$C71) | E71: =SUMIFS(Яндекс!$D:$D,Яндекс!$A:$A,"Купить",Яндекс!$B:$B,"Дом или коттедж",Яндекс!$C:$C,$C71) | F71: =SUMIFS(Авито!$E:$E,Авито!$A:$A,"Продажа",Авито!$B:$B,"Дома, дачи, коттеджи",Авито!$C:$C,$C71) | G71: =SUMIFS(Домклик!$D:$D,Домклик!$A:$A,"Покупка",Домклик!$B:$B,"Дом",Домклик!$C:$C,$C71) | H71: =IFERROR(INDEX($D$1:$G$1,MATCH(MAX(D71:G71),D71:G71,0)),"")
A72: Продажа | B72: Дома и коттеджи | C72: Санкт-Петербург | D72: =SUMIFS(ЦИАН!$D:$D,ЦИАН!$A:$A,"Продажи квартир",ЦИАН!$B:$B,"Дома и коттеджи",ЦИАН!$C:$C,$C72) | E72: =SUMIFS(Яндекс!$D:$D,Яндекс!$A:$A,"Купить",Яндекс!$B:$B,"Дом или коттедж",Яндекс!$C:$C,$C72) | F72: =SUMIFS(Авито!$E:$E,Авито!$A:$A,"Продажа",Авито!$B:$B,"Дома, дачи, коттеджи",Авито!$C:$C,$C72) | G72: =SUMIFS(Домклик!$D:$D,Домклик!$A:$A,"Покупка",Домклик!$B:$B,"Дом",Домклик!$C:$C,$C72) | H72: =IFERROR(INDEX($D$1:$G$1,MATCH(MAX(D72:G72),D72:G72,0)),"")
A73: Продажа | B73: Дома и коттеджи | C73: Новосибирск | D73: =SUMIFS(ЦИАН!$D:$D,ЦИАН!$A:$A,"Продажи квартир",ЦИАН!$B:$B,"Дома и коттеджи",ЦИАН!$C:$C,$C73) | E73: =SUMIFS(Яндекс!$D:$D,Яндекс!$A:$A,"Купить",Яндекс!$B:$B,"Дом или коттедж",Яндекс!$C:$C,$C73) | F73: =SUMIFS(Авито!$E:$E,Авито!$A:$A,"Продажа",Авито!$B:$B,"Дома, дачи, коттеджи",Авито!$C:$C,$C73) | G73: =SUMIFS(Домклик!$D:$D,Домклик!$A:$A,"Покупка",Домклик!$B:$B,"Дом",Домклик!$C:$C,$C73) | H73: =IFERROR(INDEX($D$1:$G$1,MATCH(MAX(D73:G73),D73:G73,0)),"")
A74: Продажа | B74: Дома и коттеджи | C74: Екатеринбург | D74: =SUMIFS(ЦИАН!$D:$D,ЦИАН!$A:$A,"Продажи квартир",ЦИАН!$B:$B,"Дома и коттеджи",ЦИАН!$C:$C,$C74) | E74: =SUMIFS(Яндекс!$D:$D,Яндекс!$A:$A,"Купить",Яндекс!$B:$B,"Дом или коттедж",Яндекс!$C:$C,$C74) | F74: =SUMIFS(Авито!$E:$E,Авито!$A:$A,"Продажа",Авито!$B:$B,"Дома, дачи, коттеджи",Авито!$C:$C,$C74) | G74: =SUMIFS(Домклик!$D:$D,Домклик!$A:$A,"Покупка",Домклик!$B:$B,"Дом",Домклик!$C:$C,$C74) | H74: =IFERROR(INDEX($D$1:$G$1,MATCH(MAX(D74:G74),D74:G74,0)),"")
A75: Продажа | B75: Дома и коттеджи | C75: Казань | D75: =SUMIFS(ЦИАН!$D:$D,ЦИАН!$A:$A,"Продажи квартир",ЦИАН!$B:$B,"Дома и коттеджи",ЦИАН!$C:$C,$C75) | E75: =SUMIFS(Яндекс!$D:$D,Яндекс!$A:$A,"Купить",Яндекс!$B:$B,"Дом или коттедж",Яндекс!$C:$C,$C75) | F75: =SUMIFS(Авито!$E:$E,Авито!$A:$A,"Продажа",Авито!$B:$B,"Дома, дачи, коттеджи",Авито!$C:$C,$C75) | G75: =SUMIFS(Домклик!$D:$D,Домклик!$A:$A,"Покупка",Домклик!$B:$B,"Дом",Домклик!$C:$C,$C75) | H75: =IFERROR(INDEX($D$1:$G$1,MATCH(MAX(D75:G75),D75:G75,0)),"")
A76: Продажа | B76: Дома и коттеджи | C76: Красноярск | D76: =SUMIFS(ЦИАН!$D:$D,ЦИАН!$A:$A,"Продажи квартир",ЦИАН!$B:$B,"Дома и коттеджи",ЦИАН!$C:$C,$C76) | E76: =SUMIFS(Яндекс!$D:$D,Яндекс!$A:$A,"Купить",Яндекс!$B:$B,"Дом или коттедж",Яндекс!$C:$C,$C76) | F76: =SUMIFS(Авито!$E:$E,Авито!$A:$A,"Продажа",Авито!$B:$B,"Дома, дачи, коттеджи",Авито!$C:$C,$C76) | G76: =SUMIFS(Домклик!$D:$D,Домклик!$A:$A,"Покупка",Домклик!$B:$B,"Дом",Домклик!$C:$C,$C76) | H76: =IFERROR(INDEX($D$1:$G$1,MATCH(MAX(D76:G76),D76:G76,0)),"")
A77: Продажа | B77: Дома и коттеджи | C77: Нижний Новгород | D77: =SUMIFS(ЦИАН!$D:$D,ЦИАН!$A:$A,"Продажи квартир",ЦИАН!$B:$B,"Дома и коттеджи",ЦИАН!$C:$C,$C77) | E77: =SUMIFS(Яндекс!$D:$D,Яндекс!$A:$A,"Купить",Яндекс!$B:$B,"Дом или коттедж",Яндекс!$C:$C,$C77) | F77: =SUMIFS(Авито!$E:$E,Авито!$A:$A,"Продажа",Авито!$B:$B,"Дома, дачи, коттеджи",Авито!$C:$C,$C77) | G77: =SUMIFS(Домклик!$D:$D,Домклик!$A:$A,"Покупка",Домклик!$B:$B,"Дом",Домклик!$C:$C,$C77) | H77: =IFERROR(INDEX($D$1:$G$1,MATCH(MAX(D77:G77),D77:G77,0)),"")
A78: Продажа | B78: Дома и коттеджи | C78: Челябинск | D78: =SUMIFS(ЦИАН!$D:$D,ЦИАН!$A:$A,"Продажи квартир",ЦИАН!$B:$B,"Дома и коттеджи",ЦИАН!$C:$C,$C78) | E78: =SUMIFS(Яндекс!$D:$D,Яндекс!$A:$A,"Купить",Яндекс!$B:$B,"Дом или коттедж",Яндекс!$C:$C,$C78) | F78: =SUMIFS(Авито!$E:$E,Авито!$A:$A,"Продажа",Авито!$B:$B,"Дома, дачи, коттеджи",Авито!$C:$C,$C78) | G78: =SUMIFS(Домклик!$D:$D,Домклик!$A:$A,"Покупка",Домклик!$B:$B,"Дом",Домклик!$C:$C,$C78) | H78: =IFERROR(INDEX($D$1:$G$1,MATCH(MAX(D78:G78),D78:G78,0)),"")
A79: Продажа | B79: Дома и коттеджи | C79: Уфа | D79: =SUMIFS(ЦИАН!$D:$D,ЦИАН!$A:$A,"Продажи квартир",ЦИАН!$B:$B,"Дома и коттеджи",ЦИАН!$C:$C,$C79) | E79: =SUMIFS(Яндекс!$D:$D,Яндекс!$A:$A,"Купить",Яндекс!$B:$B,"Дом или коттедж",Яндекс!$C:$C,$C79) | F79: =SUMIFS(Авито!$E:$E,Авито!$A:$A,"Продажа",Авито!$B:$B,"Дома, дачи, коттеджи",Авито!$C:$C,$C79) | G79: =SUMIFS(Домклик!$D:$D,Домклик!$A:$A,"Покупка",Домклик!$B:$B,"Дом",Домклик!$C:$C,$C79) | H79: =IFERROR(INDEX($D$1:$G$1,MATCH(MAX(D79:G79),D79:G79,0)),"")
A80: Продажа | B80: Дома и коттеджи | C80: Краснодар | D80: =SUMIFS(ЦИАН!$D:$D,ЦИАН!$A:$A,"Продажи квартир",ЦИАН!$B:$B,"Дома и коттеджи",ЦИАН!$C:$C,$C80) | E80: =SUMIFS(Яндекс!$D:$D,Яндекс!$A:$A,"Купить",Яндекс!$B:$B,"Дом или коттедж",Яндекс!$C:$C,$C80) | F80: =SUMIFS(Авито!$E:$E,Авито!$A:$A,"Продажа",Авито!$B:$B,"Дома, дачи, коттеджи",Авито!$C:$C,$C80) | G80: =SUMIFS(Домклик!$D:$D,Домклик!$A:$A,"Покупка",Домклик!$B:$B,"Дом",Домклик!$C:$C,$C80) | H80: =IFERROR(INDEX($D$1:$G$1,MATCH(MAX(D80:G80),D80:G80,0)),"")
A81: Продажа | B81: Дома и коттеджи | C81: Самара | D81: =SUMIFS(ЦИАН!$D:$D,ЦИАН!$A:$A,"Продажи квартир",ЦИАН!$B:$B,"Дома и коттеджи",ЦИАН!$C:$C,$C81) | E81: =SUMIFS(Яндекс!$D:$D,Яндекс!$A:$A,"Купить",Яндекс!$B:$B,"Дом или коттедж",Яндекс!$C:$C,$C81) | F81: =SUMIFS(Авито!$E:$E,Авито!$A:$A,"Продажа",Авито!$B:$B,"Дома, дачи, коттеджи",Авито!$C:$C,$C81) | G81: =SUMIFS(Домклик!$D:$D,Домклик!$A:$A,"Покупка",Домклик!$B:$B,"Дом",Домклик!$C:$C,$C81) | H81: =IFERROR(INDEX($D$1:$G$1,MATCH(MAX(D81:G81),D81:G81,0)),"")
... A86: Продажа | B86: Дома и коттеджи | C86: Волгоград | D86: =SUMIFS(ЦИАН!$D:$D,ЦИАН!$A:$A,"Продажи квартир",ЦИАН!$B:$B,"Дома и коттеджи",ЦИАН!$C:$C,$C86) | E86: =SUMIFS(Яндекс!$D:$D,Яндекс!$A:$A,"Купить",Яндекс!$B:$B,"Дом или коттедж",Яндекс!$C:$C,$C86) | F86: =SUMIFS(Авито!$E:$E,Авито!$A:$A,"Продажа",Авито!$B:$B,"Дома, дачи, коттеджи",Авито!$C:$C,$C86) | G86: =SUMIFS(Домклик!$D:$D,Домклик!$A:$A,"Покупка",Домклик!$B:$B,"Дом",Домклик!$C:$C,$C86) | H86: =IFERROR(INDEX($D$1:$G$1,MATCH(MAX(D86:G86),D86:G86,0)),"")
A87: Продажа | B87: Участки | C87: 🇷🇺 Вся Россия | D87: =SUMIFS(ЦИАН!$D:$D,ЦИАН!$A:$A,"Продажи квартир",ЦИАН!$B:$B,"Участки",ЦИАН!$C:$C,$C87) | E87: =SUMIFS(Яндекс!$D:$D,Яндекс!$A:$A,"Купить",Яндекс!$B:$B,"Участок",Яндекс!$C:$C,$C87) | F87: =SUMIFS(Авито!$E:$E,Авито!$A:$A,"Продажа",Авито!$B:$B,"Земельные участки",Авито!$C:$C,$C87) | G87: =SUMIFS(Домклик!$D:$D,Домклик!$A:$A,"Покупка",Домклик!$B:$B,"Участок",Домклик!$C:$C,$C87) | H87: =IFERROR(INDEX($D$1:$G$1,MATCH(MAX(D87:G87),D87:G87,0)),"")
A88: Продажа | B88: Участки | C88: Москва | D88: =SUMIFS(ЦИАН!$D:$D,ЦИАН!$A:$A,"Продажи квартир",ЦИАН!$B:$B,"Участки",ЦИАН!$C:$C,$C88) | E88: =SUMIFS(Яндекс!$D:$D,Яндекс!$A:$A,"Купить",Яндекс!$B:$B,"Участок",Яндекс!$C:$C,$C88) | F88: =SUMIFS(Авито!$E:$E,Авито!$A:$A,"Продажа",Авито!$B:$B,"Земельные участки",Авито!$C:$C,$C88) | G88: =SUMIFS(Домклик!$D:$D,Домклик!$A:$A,"Покупка",Домклик!$B:$B,"Участок",Домклик!$C:$C,$C88) | H88: =IFERROR(INDEX($D$1:$G$1,MATCH(MAX(D88:G88),D88:G88,0)),"")
A89: Продажа | B89: Участки | C89: Санкт-Петербург | D89: =SUMIFS(ЦИАН!$D:$D,ЦИАН!$A:$A,"Продажи квартир",ЦИАН!$B:$B,"Участки",ЦИАН!$C:$C,$C89) | E89: =SUMIFS(Яндекс!$D:$D,Яндекс!$A:$A,"Купить",Яндекс!$B:$B,"Участок",Яндекс!$C:$C,$C89) | F89: =SUMIFS(Авито!$E:$E,Авито!$A:$A,"Продажа",Авито!$B:$B,"Земельные участки",Авито!$C:$C,$C89) | G89: =SUMIFS(Домклик!$D:$D,Домклик!$A:$A,"Покупка",Домклик!$B:$B,"Участок",Домклик!$C:$C,$C89) | H89: =IFERROR(INDEX($D$1:$G$1,MATCH(MAX(D89:G89),D89:G89,0)),"")
A90: Продажа | B90: Участки | C90: Новосибирск | D90: =SUMIFS(ЦИАН!$D:$D,ЦИАН!$A:$A,"Продажи квартир",ЦИАН!$B:$B,"Участки",ЦИАН!$C:$C,$C90) | E90: =SUMIFS(Яндекс!$D:$D,Яндекс!$A:$A,"Купить",Яндекс!$B:$B,"Участок",Яндекс!$C:$C,$C90) | F90: =SUMIFS(Авито!$E:$E,Авито!$A:$A,"Продажа",Авито!$B:$B,"Земельные участки",Авито!$C:$C,$C90) | G90: =SUMIFS(Домклик!$D:$D,Домклик!$A:$A,"Покупка",Домклик!$B:$B,"Участок",Домклик!$C:$C,$C90) | H90: =IFERROR(INDEX($D$1:$G$1,MATCH(MAX(D90:G90),D90:G90,0)),"")
A91: Продажа | B91: Участки | C91: Екатеринбург | D91: =SUMIFS(ЦИАН!$D:$D,ЦИАН!$A:$A,"Продажи квартир",ЦИАН!$B:$B,"Участки",ЦИАН!$C:$C,$C91) | E91: =SUMIFS(Яндекс!$D:$D,Яндекс!$A:$A,"Купить",Яндекс!$B:$B,"Участок",Яндекс!$C:$C,$C91) | F91: =SUMIFS(Авито!$E:$E,Авито!$A:$A,"Продажа",Авито!$B:$B,"Земельные участки",Авито!$C:$C,$C91) | G91: =SUMIFS(Домклик!$D:$D,Домклик!$A:$A,"Покупка",Домклик!$B:$B,"Участок",Домклик!$C:$C,$C91) | H91: =IFERROR(INDEX($D$1:$G$1,MATCH(MAX(D91:G91),D91:G91,0)),"")
A92: Продажа | B92: Участки | C92: Казань | D92: =SUMIFS(ЦИАН!$D:$D,ЦИАН!$A:$A,"Продажи квартир",ЦИАН!$B:$B,"Участки",ЦИАН!$C:$C,$C92) | E92: =SUMIFS(Яндекс!$D:$D,Яндекс!$A:$A,"Купить",Яндекс!$B:$B,"Участок",Яндекс!$C:$C,$C92) | F92: =SUMIFS(Авито!$E:$E,Авито!$A:$A,"Продажа",Авито!$B:$B,"Земельные участки",Авито!$C:$C,$C92) | G92: =SUMIFS(Домклик!$D:$D,Домклик!$A:$A,"Покупка",Домклик!$B:$B,"Участок",Домклик!$C:$C,$C92) | H92: =IFERROR(INDEX($D$1:$G$1,MATCH(MAX(D92:G92),D92:G92,0)),"")
A93: Продажа | B93: Участки | C93: Красноярск | D93: =SUMIFS(ЦИАН!$D:$D,ЦИАН!$A:$A,"Продажи квартир",ЦИАН!$B:$B,"Участки",ЦИАН!$C:$C,$C93) | E93: =SUMIFS(Яндекс!$D:$D,Яндекс!$A:$A,"Купить",Яндекс!$B:$B,"Участок",Яндекс!$C:$C,$C93) | F93: =SUMIFS(Авито!$E:$E,Авито!$A:$A,"Продажа",Авито!$B:$B,"Земельные участки",Авито!$C:$C,$C93) | G93: =SUMIFS(Домклик!$D:$D,Домклик!$A:$A,"Покупка",Домклик!$B:$B,"Участок",Домклик!$C:$C,$C93) | H93: =IFERROR(INDEX($D$1:$G$1,MATCH(MAX(D93:G93),D93:G93,0)),"")
A94: Продажа | B94: Участки | C94: Нижний Новгород | D94: =SUMIFS(ЦИАН!$D:$D,ЦИАН!$A:$A,"Продажи квартир",ЦИАН!$B:$B,"Участки",ЦИАН!$C:$C,$C94) | E94: =SUMIFS(Яндекс!$D:$D,Яндекс!$A:$A,"Купить",Яндекс!$B:$B,"Участок",Яндекс!$C:$C,$C94) | F94: =SUMIFS(Авито!$E:$E,Авито!$A:$A,"Продажа",Авито!$B:$B,"Земельные участки",Авито!$C:$C,$C94) | G94: =SUMIFS(Домклик!$D:$D,Домклик!$A:$A,"Покупка",Домклик!$B:$B,"Участок",Домклик!$C:$C,$C94) | H94: =IFERROR(INDEX($D$1:$G$1,MATCH(MAX(D94:G94),D94:G94,0)),"")
A95: Продажа | B95: Участки | C95: Челябинск | D95: =SUMIFS(ЦИАН!$D:$D,ЦИАН!$A:$A,"Продажи квартир",ЦИАН!$B:$B,"Участки",ЦИАН!$C:$C,$C95) | E95: =SUMIFS(Яндекс!$D:$D,Яндекс!$A:$A,"Купить",Яндекс!$B:$B,"Участок",Яндекс!$C:$C,$C95) | F95: =SUMIFS(Авито!$E:$E,Авито!$A:$A,"Продажа",Авито!$B:$B,"Земельные участки",Авито!$C:$C,$C95) | G95: =SUMIFS(Домклик!$D:$D,Домклик!$A:$A,"Покупка",Домклик!$B:$B,"Участок",Домклик!$C:$C,$C95) | H95: =IFERROR(INDEX($D$1:$G$1,MATCH(MAX(D95:G95),D95:G95,0)),"")
A96: Продажа | B96: Участки | C96: Уфа | D96: =SUMIFS(ЦИАН!$D:$D,ЦИАН!$A:$A,"Продажи квартир",ЦИАН!$B:$B,"Участки",ЦИАН!$C:$C,$C96) | E96: =SUMIFS(Яндекс!$D:$D,Яндекс!$A:$A,"Купить",Яндекс!$B:$B,"Участок",Яндекс!$C:$C,$C96) | F96: =SUMIFS(Авито!$E:$E,Авито!$A:$A,"Продажа",Авито!$B:$B,"Земельные участки",Авито!$C:$C,$C96) | G96: =SUMIFS(Домклик!$D:$D,Домклик!$A:$A,"Покупка",Домклик!$B:$B,"Участок",Домклик!$C:$C,$C96) | H96: =IFERROR(INDEX($D$1:$G$1,MATCH(MAX(D96:G96),D96:G96,0)),"")
A97: Продажа | B97: Участки | C97: Краснодар | D97: =SUMIFS(ЦИАН!$D:$D,ЦИАН!$A:$A,"Продажи квартир",ЦИАН!$B:$B,"Участки",ЦИАН!$C:$C,$C97) | E97: =SUMIFS(Яндекс!$D:$D,Яндекс!$A:$A,"Купить",Яндекс!$B:$B,"Участок",Яндекс!$C:$C,$C97) | F97: =SUMIFS(Авито!$E:$E,Авито!$A:$A,"Продажа",Авито!$B:$B,"Земельные участки",Авито!$C:$C,$C97) | G97: =SUMIFS(Домклик!$D:$D,Домклик!$A:$A,"Покупка",Домклик!$B:$B,"Участок",Домклик!$C:$C,$C97) | H97: =IFERROR(INDEX($D$1:$G$1,MATCH(MAX(D97:G97),D97:G97,0)),"")
A98: Продажа | B98: Участки | C98: Самара | D98: =SUMIFS(ЦИАН!$D:$D,ЦИАН!$A:$A,"Продажи квартир",ЦИАН!$B:$B,"Участки",ЦИАН!$C:$C,$C98) | E98: =SUMIFS(Яндекс!$D:$D,Яндекс!$A:$A,"Купить",Яндекс!$B:$B,"Участок",Яндекс!$C:$C,$C98) | F98: =SUMIFS(Авито!$E:$E,Авито!$A:$A,"Продажа",Авито!$B:$B,"Земельные участки",Авито!$C:$C,$C98) | G98: =SUMIFS(Домклик!$D:$D,Домклик!$A:$A,"Покупка",Домклик!$B:$B,"Участок",Домклик!$C:$C,$C98) | H98: =IFERROR(INDEX($D$1:$G$1,MATCH(MAX(D98:G98),D98:G98,0)),"")
... A103: Продажа | B103: Участки | C103: Волгоград | D103: =SUMIFS(ЦИАН!$D:$D,ЦИАН!$A:$A,"Продажи квартир",ЦИАН!$B:$B,"Участки",ЦИАН!$C:$C,$C103) | E103: =SUMIFS(Яндекс!$D:$D,Яндекс!$A:$A,"Купить",Яндекс!$B:$B,"Участок",Яндекс!$C:$C,$C103) | F103: =SUMIFS(Авито!$E:$E,Авито!$A:$A,"Продажа",Авито!$B:$B,"Земельные участки",Авито!$C:$C,$C103) | G103: =SUMIFS(Домклик!$D:$D,Домклик!$A:$A,"Покупка",Домклик!$B:$B,"Участок",Домклик!$C:$C,$C103) | H103: =IFERROR(INDEX($D$1:$G$1,MATCH(MAX(D103:G103),D103:G103,0)),"")
A104: Продажа | B104: Коммерческая | C104: 🇷🇺 Вся Россия | D104: =SUMIFS(ЦИАН!$D:$D,ЦИАН!$A:$A,"Коммерческая · Продажа",ЦИАН!$B:$B,"Офис",ЦИАН!$C:$C,$C104)+SUMIFS(ЦИАН!$D:$D,ЦИАН!$A:$A,"Коммерческая · Продажа",ЦИАН!$B:$B,"Торговая площадь",ЦИАН!$C:$C,$C104)+SUMIFS(ЦИАН!$D:$D,ЦИАН!$A:$A,"Коммерческая · Продажа",ЦИАН!$B:$B,"Складское помещение",ЦИАН!$C:$C,$C104)+SUMIFS(ЦИАН!$D:$D,ЦИАН!$A:$A,"Коммерческая · Продажа",ЦИАН!$B:$B,"Бизнес (готовый)",ЦИАН!$C:$C,$C104) | E104: =SUMIFS(Яндекс!$D:$D,Яндекс!$A:$A,"Коммерческая",Яндекс!$B:$B,"Продажа",Яндекс!$C:$C,$C104) | F104: =SUMIFS(Авито!$E:$E,Авито!$A:$A,"Продажа",Авито!$B:$B,"Коммерческая",Авито!$C:$C,$C104) | G104: =SUMIFS(Домклик!$D:$D,Домклик!$A:$A,"Покупка",Домклик!$B:$B,"Коммерческая",Домклик!$C:$C,$C104) | H104: =IFERROR(INDEX($D$1:$G$1,MATCH(MAX(D104:G104),D104:G104,0)),"")
A105: Продажа | B105: Коммерческая | C105: Москва | D105: =SUMIFS(ЦИАН!$D:$D,ЦИАН!$A:$A,"Коммерческая · Продажа",ЦИАН!$B:$B,"Офис",ЦИАН!$C:$C,$C105)+SUMIFS(ЦИАН!$D:$D,ЦИАН!$A:$A,"Коммерческая · Продажа",ЦИАН!$B:$B,"Торговая площадь",ЦИАН!$C:$C,$C105)+SUMIFS(ЦИАН!$D:$D,ЦИАН!$A:$A,"Коммерческая · Продажа",ЦИАН!$B:$B,"Складское помещение",ЦИАН!$C:$C,$C105)+SUMIFS(ЦИАН!$D:$D,ЦИАН!$A:$A,"Коммерческая · Продажа",ЦИАН!$B:$B,"Бизнес (готовый)",ЦИАН!$C:$C,$C105) | E105: =SUMIFS(Яндекс!$D:$D,Яндекс!$A:$A,"Коммерческая",Яндекс!$B:$B,"Продажа",Яндекс!$C:$C,$C105) | F105: =SUMIFS(Авито!$E:$E,Авито!$A:$A,"Продажа",Авито!$B:$B,"Коммерческая",Авито!$C:$C,$C105) | G105: =SUMIFS(Домклик!$D:$D,Домклик!$A:$A,"Покупка",Домклик!$B:$B,"Коммерческая",Домклик!$C:$C,$C105) | H105: =IFERROR(INDEX($D$1:$G$1,MATCH(MAX(D105:G105),D105:G105,0)),"")
A106: Продажа | B106: Коммерческая | C106: Санкт-Петербург | D106: =SUMIFS(ЦИАН!$D:$D,ЦИАН!$A:$A,"Коммерческая · Продажа",ЦИАН!$B:$B,"Офис",ЦИАН!$C:$C,$C106)+SUMIFS(ЦИАН!$D:$D,ЦИАН!$A:$A,"Коммерческая · Продажа",ЦИАН!$B:$B,"Торговая площадь",ЦИАН!$C:$C,$C106)+SUMIFS(ЦИАН!$D:$D,ЦИАН!$A:$A,"Коммерческая · Продажа",ЦИАН!$B:$B,"Складское помещение",ЦИАН!$C:$C,$C106)+SUMIFS(ЦИАН!$D:$D,ЦИАН!$A:$A,"Коммерческая · Продажа",ЦИАН!$B:$B,"Бизнес (готовый)",ЦИАН!$C:$C,$C106) | E106: =SUMIFS(Яндекс!$D:$D,Яндекс!$A:$A,"Коммерческая",Яндекс!$B:$B,"Продажа",Яндекс!$C:$C,$C106) | F106: =SUMIFS(Авито!$E:$E,Авито!$A:$A,"Продажа",Авито!$B:$B,"Коммерческая",Авито!$C:$C,$C106) | G106: =SUMIFS(Домклик!$D:$D,Домклик!$A:$A,"Покупка",Домклик!$B:$B,"Коммерческая",Домклик!$C:$C,$C106) | H106: =IFERROR(INDEX($D$1:$G$1,MATCH(MAX(D106:G106),D106:G106,0)),"")
A107: Продажа | B107: Коммерческая | C107: Новосибирск | D107: =SUMIFS(ЦИАН!$D:$D,ЦИАН!$A:$A,"Коммерческая · Продажа",ЦИАН!$B:$B,"Офис",ЦИАН!$C:$C,$C107)+SUMIFS(ЦИАН!$D:$D,ЦИАН!$A:$A,"Коммерческая · Продажа",ЦИАН!$B:$B,"Торговая площадь",ЦИАН!$C:$C,$C107)+SUMIFS(ЦИАН!$D:$D,ЦИАН!$A:$A,"Коммерческая · Продажа",ЦИАН!$B:$B,"Складское помещение",ЦИАН!$C:$C,$C107)+SUMIFS(ЦИАН!$D:$D,ЦИАН!$A:$A,"Коммерческая · Продажа",ЦИАН!$B:$B,"Бизнес (готовый)",ЦИАН!$C:$C,$C107) | E107: =SUMIFS(Яндекс!$D:$D,Яндекс!$A:$A,"Коммерческая",Яндекс!$B:$B,"Продажа",Яндекс!$C:$C,$C107) | F107: =SUMIFS(Авито!$E:$E,Авито!$A:$A,"Продажа",Авито!$B:$B,"Коммерческая",Авито!$C:$C,$C107) | G107: =SUMIFS(Домклик!$D:$D,Домклик!$A:$A,"Покупка",Домклик!$B:$B,"Коммерческая",Домклик!$C:$C,$C107) | H107: =IFERROR(INDEX($D$1:$G$1,MATCH(MAX(D107:G107),D107:G107,0)),"")
A108: Продажа | B108: Коммерческая | C108: Екатеринбург | D108: =SUMIFS(ЦИАН!$D:$D,ЦИАН!$A:$A,"Коммерческая · Продажа",ЦИАН!$B:$B,"Офис",ЦИАН!$C:$C,$C108)+SUMIFS(ЦИАН!$D:$D,ЦИАН!$A:$A,"Коммерческая · Продажа",ЦИАН!$B:$B,"Торговая площадь",ЦИАН!$C:$C,$C108)+SUMIFS(ЦИАН!$D:$D,ЦИАН!$A:$A,"Коммерческая · Продажа",ЦИАН!$B:$B,"Складское помещение",ЦИАН!$C:$C,$C108)+SUMIFS(ЦИАН!$D:$D,ЦИАН!$A:$A,"Коммерческая · Продажа",ЦИАН!$B:$B,"Бизнес (готовый)",ЦИАН!$C:$C,$C108) | E108: =SUMIFS(Яндекс!$D:$D,Яндекс!$A:$A,"Коммерческая",Яндекс!$B:$B,"Продажа",Яндекс!$C:$C,$C108) | F108: =SUMIFS(Авито!$E:$E,Авито!$A:$A,"Продажа",Авито!$B:$B,"Коммерческая",Авито!$C:$C,$C108) | G108: =SUMIFS(Домклик!$D:$D,Домклик!$A:$A,"Покупка",Домклик!$B:$B,"Коммерческая",Домклик!$C:$C,$C108) | H108: =IFERROR(INDEX($D$1:$G$1,MATCH(MAX(D108:G108),D108:G108,0)),"")
A109: Продажа | B109: Коммерческая | C109: Казань | D109: =SUMIFS(ЦИАН!$D:$D,ЦИАН!$A:$A,"Коммерческая · Продажа",ЦИАН!$B:$B,"Офис",ЦИАН!$C:$C,$C109)+SUMIFS(ЦИАН!$D:$D,ЦИАН!$A:$A,"Коммерческая · Продажа",ЦИАН!$B:$B,"Торговая площадь",ЦИАН!$C:$C,$C109)+SUMIFS(ЦИАН!$D:$D,ЦИАН!$A:$A,"Коммерческая · Продажа",ЦИАН!$B:$B,"Складское помещение",ЦИАН!$C:$C,$C109)+SUMIFS(ЦИАН!$D:$D,ЦИАН!$A:$A,"Коммерческая · Продажа",ЦИАН!$B:$B,"Бизнес (готовый)",ЦИАН!$C:$C,$C109) | E109: =SUMIFS(Яндекс!$D:$D,Яндекс!$A:$A,"Коммерческая",Яндекс!$B:$B,"Продажа",Яндекс!$C:$C,$C109) | F109: =SUMIFS(Авито!$E:$E,Авито!$A:$A,"Продажа",Авито!$B:$B,"Коммерческая",Авито!$C:$C,$C109) | G109: =SUMIFS(Домклик!$D:$D,Домклик!$A:$A,"Покупка",Домклик!$B:$B,"Коммерческая",Домклик!$C:$C,$C109) | H109: =IFERROR(INDEX($D$1:$G$1,MATCH(MAX(D109:G109),D109:G109,0)),"")
A110: Продажа | B110: Коммерческая | C110: Красноярск | D110: =SUMIFS(ЦИАН!$D:$D,ЦИАН!$A:$A,"Коммерческая · Продажа",ЦИАН!$B:$B,"Офис",ЦИАН!$C:$C,$C110)+SUMIFS(ЦИАН!$D:$D,ЦИАН!$A:$A,"Коммерческая · Продажа",ЦИАН!$B:$B,"Торговая площадь",ЦИАН!$C:$C,$C110)+SUMIFS(ЦИАН!$D:$D,ЦИАН!$A:$A,"Коммерческая · Продажа",ЦИАН!$B:$B,"Складское помещение",ЦИАН!$C:$C,$C110)+SUMIFS(ЦИАН!$D:$D,ЦИАН!$A:$A,"Коммерческая · Продажа",ЦИАН!$B:$B,"Бизнес (готовый)",ЦИАН!$C:$C,$C110) | E110: =SUMIFS(Яндекс!$D:$D,Яндекс!$A:$A,"Коммерческая",Яндекс!$B:$B,"Продажа",Яндекс!$C:$C,$C110) | F110: =SUMIFS(Авито!$E:$E,Авито!$A:$A,"Продажа",Авито!$B:$B,"Коммерческая",Авито!$C:$C,$C110) | G110: =SUMIFS(Домклик!$D:$D,Домклик!$A:$A,"Покупка",Домклик!$B:$B,"Коммерческая",Домклик!$C:$C,$C110) | H110: =IFERROR(INDEX($D$1:$G$1,MATCH(MAX(D110:G110),D110:G110,0)),"")
A111: Продажа | B111: Коммерческая | C111: Нижний Новгород | D111: =SUMIFS(ЦИАН!$D:$D,ЦИАН!$A:$A,"Коммерческая · Продажа",ЦИАН!$B:$B,"Офис",ЦИАН!$C:$C,$C111)+SUMIFS(ЦИАН!$D:$D,ЦИАН!$A:$A,"Коммерческая · Продажа",ЦИАН!$B:$B,"Торговая площадь",ЦИАН!$C:$C,$C111)+SUMIFS(ЦИАН!$D:$D,ЦИАН!$A:$A,"Коммерческая · Продажа",ЦИАН!$B:$B,"Складское помещение",ЦИАН!$C:$C,$C111)+SUMIFS(ЦИАН!$D:$D,ЦИАН!$A:$A,"Коммерческая · Продажа",ЦИАН!$B:$B,"Бизнес (готовый)",ЦИАН!$C:$C,$C111) | E111: =SUMIFS(Яндекс!$D:$D,Яндекс!$A:$A,"Коммерческая",Яндекс!$B:$B,"Продажа",Яндекс!$C:$C,$C111) | F111: =SUMIFS(Авито!$E:$E,Авито!$A:$A,"Продажа",Авито!$B:$B,"Коммерческая",Авито!$C:$C,$C111) | G111: =SUMIFS(Домклик!$D:$D,Домклик!$A:$A,"Покупка",Домклик!$B:$B,"Коммерческая",Домклик!$C:$C,$C111) | H111: =IFERROR(INDEX($D$1:$G$1,MATCH(MAX(D111:G111),D111:G111,0)),"")
A112: Продажа | B112: Коммерческая | C112: Челябинск | D112: =SUMIFS(ЦИАН!$D:$D,ЦИАН!$A:$A,"Коммерческая · Продажа",ЦИАН!$B:$B,"Офис",ЦИАН!$C:$C,$C112)+SUMIFS(ЦИАН!$D:$D,ЦИАН!$A:$A,"Коммерческая · Продажа",ЦИАН!$B:$B,"Торговая площадь",ЦИАН!$C:$C,$C112)+SUMIFS(ЦИАН!$D:$D,ЦИАН!$A:$A,"Коммерческая · Продажа",ЦИАН!$B:$B,"Складское помещение",ЦИАН!$C:$C,$C112)+SUMIFS(ЦИАН!$D:$D,ЦИАН!$A:$A,"Коммерческая · Продажа",ЦИАН!$B:$B,"Бизнес (готовый)",ЦИАН!$C:$C,$C112) | E112: =SUMIFS(Яндекс!$D:$D,Яндекс!$A:$A,"Коммерческая",Яндекс!$B:$B,"Продажа",Яндекс!$C:$C,$C112) | F112: =SUMIFS(Авито!$E:$E,Авито!$A:$A,"Продажа",Авито!$B:$B,"Коммерческая",Авито!$C:$C,$C112) | G112: =SUMIFS(Домклик!$D:$D,Домклик!$A:$A,"Покупка",Домклик!$B:$B,"Коммерческая",Домклик!$C:$C,$C112) | H112: =IFERROR(INDEX($D$1:$G$1,MATCH(MAX(D112:G112),D112:G112,0)),"")
A113: Продажа | B113: Коммерческая | C113: Уфа | D113: =SUMIFS(ЦИАН!$D:$D,ЦИАН!$A:$A,"Коммерческая · Продажа",ЦИАН!$B:$B,"Офис",ЦИАН!$C:$C,$C113)+SUMIFS(ЦИАН!$D:$D,ЦИАН!$A:$A,"Коммерческая · Продажа",ЦИАН!$B:$B,"Торговая площадь",ЦИАН!$C:$C,$C113)+SUMIFS(ЦИАН!$D:$D,ЦИАН!$A:$A,"Коммерческая · Продажа",ЦИАН!$B:$B,"Складское помещение",ЦИАН!$C:$C,$C113)+SUMIFS(ЦИАН!$D:$D,ЦИАН!$A:$A,"Коммерческая · Продажа",ЦИАН!$B:$B,"Бизнес (готовый)",ЦИАН!$C:$C,$C113) | E113: =SUMIFS(Яндекс!$D:$D,Яндекс!$A:$A,"Коммерческая",Яндекс!$B:$B,"Продажа",Яндекс!$C:$C,$C113) | F113: =SUMIFS(Авито!$E:$E,Авито!$A:$A,"Продажа",Авито!$B:$B,"Коммерческая",Авито!$C:$C,$C113) | G113: =SUMIFS(Домклик!$D:$D,Домклик!$A:$A,"Покупка",Домклик!$B:$B,"Коммерческая",Домклик!$C:$C,$C113) | H113: =IFERROR(INDEX($D$1:$G$1,MATCH(MAX(D113:G113),D113:G113,0)),"")
A114: Продажа | B114: Коммерческая | C114: Краснодар | D114: =SUMIFS(ЦИАН!$D:$D,ЦИАН!$A:$A,"Коммерческая · Продажа",ЦИАН!$B:$B,"Офис",ЦИАН!$C:$C,$C114)+SUMIFS(ЦИАН!$D:$D,ЦИАН!$A:$A,"Коммерческая · Продажа",ЦИАН!$B:$B,"Торговая площадь",ЦИАН!$C:$C,$C114)+SUMIFS(ЦИАН!$D:$D,ЦИАН!$A:$A,"Коммерческая · Продажа",ЦИАН!$B:$B,"Складское помещение",ЦИАН!$C:$C,$C114)+SUMIFS(ЦИАН!$D:$D,ЦИАН!$A:$A,"Коммерческая · Продажа",ЦИАН!$B:$B,"Бизнес (готовый)",ЦИАН!$C:$C,$C114) | E114: =SUMIFS(Яндекс!$D:$D,Яндекс!$A:$A,"Коммерческая",Яндекс!$B:$B,"Продажа",Яндекс!$C:$C,$C114) | F114: =SUMIFS(Авито!$E:$E,Авито!$A:$A,"Продажа",Авито!$B:$B,"Коммерческая",Авито!$C:$C,$C114) | G114: =SUMIFS(Домклик!$D:$D,Домклик!$A:$A,"Покупка",Домклик!$B:$B,"Коммерческая",Домклик!$C:$C,$C114) | H114: =IFERROR(INDEX($D$1:$G$1,MATCH(MAX(D114:G114),D114:G114,0)),"")
A115: Продажа | B115: Коммерческая | C115: Самара | D115: =SUMIFS(ЦИАН!$D:$D,ЦИАН!$A:$A,"Коммерческая · Продажа",ЦИАН!$B:$B,"Офис",ЦИАН!$C:$C,$C115)+SUMIFS(ЦИАН!$D:$D,ЦИАН!$A:$A,"Коммерческая · Продажа",ЦИАН!$B:$B,"Торговая площадь",ЦИАН!$C:$C,$C115)+SUMIFS(ЦИАН!$D:$D,ЦИАН!$A:$A,"Коммерческая · Продажа",ЦИАН!$B:$B,"Складское помещение",ЦИАН!$C:$C,$C115)+SUMIFS(ЦИАН!$D:$D,ЦИАН!$A:$A,"Коммерческая · Продажа",ЦИАН!$B:$B,"Бизнес (готовый)",ЦИАН!$C:$C,$C115) | E115: =SUMIFS(Яндекс!$D:$D,Яндекс!$A:$A,"Коммерческая",Яндекс!$B:$B,"Продажа",Яндекс!$C:$C,$C115) | F115: =SUMIFS(Авито!$E:$E,Авито!$A:$A,"Продажа",Авито!$B:$B,"Коммерческая",Авито!$C:$C,$C115) | G115: =SUMIFS(Домклик!$D:$D,Домклик!$A:$A,"Покупка",Домклик!$B:$B,"Коммерческая",Домклик!$C:$C,$C115) | H115: =IFERROR(INDEX($D$1:$G$1,MATCH(MAX(D115:G115),D115:G115,0)),"")
... A120: Продажа | B120: Коммерческая | C120: Волгоград | D120: =SUMIFS(ЦИАН!$D:$D,ЦИАН!$A:$A,"Коммерческая · Продажа",ЦИАН!$B:$B,"Офис",ЦИАН!$C:$C,$C120)+SUMIFS(ЦИАН!$D:$D,ЦИАН!$A:$A,"Коммерческая · Продажа",ЦИАН!$B:$B,"Торговая площадь",ЦИАН!$C:$C,$C120)+SUMIFS(ЦИАН!$D:$D,ЦИАН!$A:$A,"Коммерческая · Продажа",ЦИАН!$B:$B,"Складское помещение",ЦИАН!$C:$C,$C120)+SUMIFS(ЦИАН!$D:$D,ЦИАН!$A:$A,"Коммерческая · Продажа",ЦИАН!$B:$B,"Бизнес (готовый)",ЦИАН!$C:$C,$C120) | E120: =SUMIFS(Яндекс!$D:$D,Яндекс!$A:$A,"Коммерческая",Яндекс!$B:$B,"Продажа",Яндекс!$C:$C,$C120) | F120: =SUMIFS(Авито!$E:$E,Авито!$A:$A,"Продажа",Авито!$B:$B,"Коммерческая",Авито!$C:$C,$C120) | G120: =SUMIFS(Домклик!$D:$D,Домклик!$A:$A,"Покупка",Домклик!$B:$B,"Коммерческая",Домклик!$C:$C,$C120) | H120: =IFERROR(INDEX($D$1:$G$1,MATCH(MAX(D120:G120),D120:G120,0)),"")
A121: Аренда | B121: Квартиры | C121: 🇷🇺 Вся Россия | D121: =SUMIFS(ЦИАН!$D:$D,ЦИАН!$A:$A,"Аренда квартир",ЦИАН!$B:$B,"Длительная: Квартиры",ЦИАН!$C:$C,$C121) | E121: =SUMIFS(Яндекс!$D:$D,Яндекс!$A:$A,"Снять",Яндекс!$B:$B,"Квартира",Яндекс!$C:$C,$C121) | F121: =SUMIFS(Авито!$E:$E,Авито!$A:$A,"Аренда",Авито!$B:$B,"Квартиры долгосрочно",Авито!$C:$C,$C121) | G121: =SUMIFS(Домклик!$D:$D,Домклик!$A:$A,"Аренда",Домклик!$B:$B,"Квартиры",Домклик!$C:$C,$C121) | H121: =IFERROR(INDEX($D$1:$G$1,MATCH(MAX(D121:G121),D121:G121,0)),"")
A122: Аренда | B122: Квартиры | C122: Москва | D122: =SUMIFS(ЦИАН!$D:$D,ЦИАН!$A:$A,"Аренда квартир",ЦИАН!$B:$B,"Длительная: Квартиры",ЦИАН!$C:$C,$C122) | E122: =SUMIFS(Яндекс!$D:$D,Яндекс!$A:$A,"Снять",Яндекс!$B:$B,"Квартира",Яндекс!$C:$C,$C122) | F122: =SUMIFS(Авито!$E:$E,Авито!$A:$A,"Аренда",Авито!$B:$B,"Квартиры долгосрочно",Авито!$C:$C,$C122) | G122: =SUMIFS(Домклик!$D:$D,Домклик!$A:$A,"Аренда",Домклик!$B:$B,"Квартиры",Домклик!$C:$C,$C122) | H122: =IFERROR(INDEX($D$1:$G$1,MATCH(MAX(D122:G122),D122:G122,0)),"")
A123: Аренда | B123: Квартиры | C123: Санкт-Петербург | D123: =SUMIFS(ЦИАН!$D:$D,ЦИАН!$A:$A,"Аренда квартир",ЦИАН!$B:$B,"Длительная: Квартиры",ЦИАН!$C:$C,$C123) | E123: =SUMIFS(Яндекс!$D:$D,Яндекс!$A:$A,"Снять",Яндекс!$B:$B,"Квартира",Яндекс!$C:$C,$C123) | F123: =SUMIFS(Авито!$E:$E,Авито!$A:$A,"Аренда",Авито!$B:$B,"Квартиры долгосрочно",Авито!$C:$C,$C123) | G123: =SUMIFS(Домклик!$D:$D,Домклик!$A:$A,"Аренда",Домклик!$B:$B,"Квартиры",Домклик!$C:$C,$C123) | H123: =IFERROR(INDEX($D$1:$G$1,MATCH(MAX(D123:G123),D123:G123,0)),"")
A124: Аренда | B124: Квартиры | C124: Новосибирск | D124: =SUMIFS(ЦИАН!$D:$D,ЦИАН!$A:$A,"Аренда квартир",ЦИАН!$B:$B,"Длительная: Квартиры",ЦИАН!$C:$C,$C124) | E124: =SUMIFS(Яндекс!$D:$D,Яндекс!$A:$A,"Снять",Яндекс!$B:$B,"Квартира",Яндекс!$C:$C,$C124) | F124: =SUMIFS(Авито!$E:$E,Авито!$A:$A,"Аренда",Авито!$B:$B,"Квартиры долгосрочно",Авито!$C:$C,$C124) | G124: =SUMIFS(Домклик!$D:$D,Домклик!$A:$A,"Аренда",Домклик!$B:$B,"Квартиры",Домклик!$C:$C,$C124) | H124: =IFERROR(INDEX($D$1:$G$1,MATCH(MAX(D124:G124),D124:G124,0)),"")
A125: Аренда | B125: Квартиры | C125: Екатеринбург | D125: =SUMIFS(ЦИАН!$D:$D,ЦИАН!$A:$A,"Аренда квартир",ЦИАН!$B:$B,"Длительная: Квартиры",ЦИАН!$C:$C,$C125) | E125: =SUMIFS(Яндекс!$D:$D,Яндекс!$A:$A,"Снять",Яндекс!$B:$B,"Квартира",Яндекс!$C:$C,$C125) | F125: =SUMIFS(Авито!$E:$E,Авито!$A:$A,"Аренда",Авито!$B:$B,"Квартиры долгосрочно",Авито!$C:$C,$C125) | G125: =SUMIFS(Домклик!$D:$D,Домклик!$A:$A,"Аренда",Домклик!$B:$B,"Квартиры",Домклик!$C:$C,$C125) | H125: =IFERROR(INDEX($D$1:$G$1,MATCH(MAX(D125:G125),D125:G125,0)),"")
A126: Аренда | B126: Квартиры | C126: Казань | D126: =SUMIFS(ЦИАН!$D:$D,ЦИАН!$A:$A,"Аренда квартир",ЦИАН!$B:$B,"Длительная: Квартиры",ЦИАН!$C:$C,$C126) | E126: =SUMIFS(Яндекс!$D:$D,Яндекс!$A:$A,"Снять",Яндекс!$B:$B,"Квартира",Яндекс!$C:$C,$C126) | F126: =SUMIFS(Авито!$E:$E,Авито!$A:$A,"Аренда",Авито!$B:$B,"Квартиры долгосрочно",Авито!$C:$C,$C126) | G126: =SUMIFS(Домклик!$D:$D,Домклик!$A:$A,"Аренда",Домклик!$B:$B,"Квартиры",Домклик!$C:$C,$C126) | H126: =IFERROR(INDEX($D$1:$G$1,MATCH(MAX(D126:G126),D126:G126,0)),"")
A127: Аренда | B127: Квартиры | C127: Красноярск | D127: =SUMIFS(ЦИАН!$D:$D,ЦИАН!$A:$A,"Аренда квартир",ЦИАН!$B:$B,"Длительная: Квартиры",ЦИАН!$C:$C,$C127) | E127: =SUMIFS(Яндекс!$D:$D,Яндекс!$A:$A,"Снять",Яндекс!$B:$B,"Квартира",Яндекс!$C:$C,$C127) | F127: =SUMIFS(Авито!$E:$E,Авито!$A:$A,"Аренда",Авито!$B:$B,"Квартиры долгосрочно",Авито!$C:$C,$C127) | G127: =SUMIFS(Домклик!$D:$D,Домклик!$A:$A,"Аренда",Домклик!$B:$B,"Квартиры",Домклик!$C:$C,$C127) | H127: =IFERROR(INDEX($D$1:$G$1,MATCH(MAX(D127:G127),D127:G127,0)),"")
A128: Аренда | B128: Квартиры | C128: Нижний Новгород | D128: =SUMIFS(ЦИАН!$D:$D,ЦИАН!$A:$A,"Аренда квартир",ЦИАН!$B:$B,"Длительная: Квартиры",ЦИАН!$C:$C,$C128) | E128: =SUMIFS(Яндекс!$D:$D,Яндекс!$A:$A,"Снять",Яндекс!$B:$B,"Квартира",Яндекс!$C:$C,$C128) | F128: =SUMIFS(Авито!$E:$E,Авито!$A:$A,"Аренда",Авито!$B:$B,"Квартиры долгосрочно",Авито!$C:$C,$C128) | G128: =SUMIFS(Домклик!$D:$D,Домклик!$A:$A,"Аренда",Домклик!$B:$B,"Квартиры",Домклик!$C:$C,$C128) | H128: =IFERROR(INDEX($D$1:$G$1,MATCH(MAX(D128:G128),D128:G128,0)),"")
...

Sheet ЦИАН
A1: Группа | B1: Категория | C1: Город | D1: 2026-06-10
A2: Аренда квартир | B2: Длительная: Квартиры | C2: 🇷🇺 Вся Россия | D2: 125508
A3: Аренда квартир | B3: Длительная: Квартиры | C3: Москва | D3: 27204
A4: Аренда квартир | B4: Длительная: Квартиры | C4: Санкт-Петербург | D4: 9761
A5: Аренда квартир | B5: Длительная: Квартиры | C5: Новосибирск | D5: 4836
A6: Аренда квартир | B6: Длительная: Квартиры | C6: Екатеринбург | D6: 3235
A7: Аренда квартир | B7: Длительная: Квартиры | C7: Казань | D7: 3843
A8: Аренда квартир | B8: Длительная: Квартиры | C8: Красноярск | D8: 1825
A9: Аренда квартир | B9: Длительная: Квартиры | C9: Нижний Новгород | D9: 1427
A10: Аренда квартир | B10: Длительная: Квартиры | C10: Челябинск | D10: 1394
A11: Аренда квартир | B11: Длительная: Квартиры | C11: Уфа | D11: 1831
A12: Аренда квартир | B12: Длительная: Квартиры | C12: Краснодар | D12: 5854
A13: Аренда квартир | B13: Длительная: Квартиры | C13: Самара | D13: 1163
... A355: Коммерческая · Спец-объекты | B355: Складские комплексы | C355: Волгоград | D355: 5
A357: Итого (по фильтру) | C357: ← сумма видимых строк (без «Вся Россия») | D357: =SUMPRODUCT(SUBTOTAL(109,OFFSET(D$2,ROW(D$2:D$355)-ROW(D$2),0)),--($C$2:$C$355<>"🇷🇺 Вся Россия"))

Sheet Вся Россия (регионы)
A1: Группа | B1: Категория | C1: Регион | D1: 2026-06-10
A2: Аренда квартир | B2: Длительная: Квартиры | C2: Москва | D2: 27241
A3: Аренда квартир | B3: Длительная: Квартиры | C3: Санкт-Петербург | D3: 9781
A4: Аренда квартир | B4: Длительная: Квартиры | C4: Республика Адыгея | D4: 372
A5: Аренда квартир | B5: Длительная: Квартиры | C5: Республика Алтай | D5: 27
A6: Аренда квартир | B6: Длительная: Квартиры | C6: Алтайский край | D6: 570
A7: Аренда квартир | B7: Длительная: Квартиры | C7: Амурская область | D7: 107
A8: Аренда квартир | B8: Длительная: Квартиры | C8: Архангельская область | D8: 173
A9: Аренда квартир | B9: Длительная: Квартиры | C9: Астраханская область | D9: 358
A10: Аренда квартир | B10: Длительная: Квартиры | C10: Республика Башкортостан | D10: 2052
A11: Аренда квартир | B11: Длительная: Квартиры | C11: Белгородская область | D11: 4156
A12: Аренда квартир | B12: Длительная: Квартиры | C12: Брянская область | D12: 399
A13: Аренда квартир | B13: Длительная: Квартиры | C13: Республика Бурятия | D13: 149
... A1531: Коммерческая · Продажа | B1531: Бизнес (готовый) | C1531: Забайкальский край | D1531: 24
A1533: Итого (по фильтру) | D1533: =SUBTOTAL(109,D2:D1531)

Sheet CIAN Price
A1: Сделка | B1: Тип недвижимости | C1: Категория | D1: Город | E1: Публикация, ₽/30 дн | F1: Топ, ₽/сут | G1: Премиум, ₽/сут | H1: Стандарт, ₽/сут | I1: Примечание | J1: Обновлено
A2: Продажа | B2: Городская | C2: Квартира | D2: Москва | E2: 3390 | F2: 1213 | G2: 492 | H2: 162 | I2: Цена зависит от стоимости объекта | J2: 2026-06-10
A3: Продажа | B3: Городская | C3: Квартира | D3: Санкт-Петербург | E3: 1560 | F3: 598 | G3: 255 | H3: 108 | I3: Цена зависит от стоимости объекта | J3: 2026-06-10
A4: Продажа | B4: Городская | C4: Квартира | D4: Новосибирск | E4: 1596 | F4: 420 | G4: 189 | H4: 56 | I4: Цена зависит от стоимости объекта | J4: 2026-06-10
A5: Продажа | B5: Городская | C5: Квартира | D5: Екатеринбург | E5: 489 | F5: 396 | G5: 205 | H5: 62 | I5: Цена зависит от стоимости объекта | J5: 2026-06-10
A6: Продажа | B6: Городская | C6: Квартира | D6: Казань | E6: 354 | F6: 222 | G6: 86 | H6: 25 | I6: Цена зависит от стоимости объекта | J6: 2026-06-10
A7: Продажа | B7: Городская | C7: Квартира | D7: Красноярск | E7: 573 | F7: — | G7: — | H7: — | I7: Цена зависит от стоимости объекта | J7: 2026-06-10
A8: Продажа | B8: Городская | C8: Квартира | D8: Нижний Новгород | E8: 441 | F8: 208 | G8: 81 | H8: 23 | I8: Цена зависит от стоимости объекта | J8: 2026-06-10
A9: Продажа | B9: Городская | C9: Квартира | D9: Челябинск | E9: 291 | F9: 203 | G9: 95 | H9: 27 | I9: Цена зависит от стоимости объекта | J9: 2026-06-10
A10: Продажа | B10: Городская | C10: Квартира | D10: Уфа | E10: 213 | F10: 176 | G10: 80 | H10: 23 | I10: Цена зависит от стоимости объекта | J10: 2026-06-10
A11: Продажа | B11: Городская | C11: Квартира | D11: Краснодар | E11: 468 | F11: 197 | G11: 79 | H11: 24 | I11: Цена зависит от стоимости объекта | J11: 2026-06-10
A12: Продажа | B12: Городская | C12: Квартира | D12: Самара | E12: 354 | F12: — | G12: — | H12: — | I12: Цена зависит от стоимости объекта | J12: 2026-06-10
A13: Продажа | B13: Городская | C13: Квартира | D13: Ростов-на-Дону | E13: 468 | F13: 214 | G13: 87 | H13: 26 | I13: Цена зависит от стоимости объекта | J13: 2026-06-10
A14: Продажа | B14: Городская | C14: Квартира | D14: Омск | E14: 780 | F14: 345 | G14: 187 | H14: 58 | I14: Цена зависит от стоимости объекта | J14: 2026-06-10
A15: Продажа | B15: Городская | C15: Квартира | D15: Воронеж | E15: 204 | F15: — | G15: — | H15: — | I15: Цена зависит от стоимости объекта | J15: 2026-06-10
A16: Продажа | B16: Городская | C16: Квартира | D16: Пермь | E16: 99 | F16: — | G16: — | H16: — | I16: Цена зависит от стоимости объекта | J16: 2026-06-10
A17: Продажа | B17: Городская | C17: Квартира | D17: Волгоград | E17: 303 | F17: — | G17: — | H17: — | I17: Цена зависит от стоимости объекта | J17: 2026-06-10
A18: Продажа | B18: Городская | C18: Комната | D18: Москва | E18: 3120 | F18: 904 | G18: 382 | H18: 116 | I18: Цена зависит от стоимости объекта | J18: 2026-06-10
A19: Продажа | B19: Городская | C19: Комната | D19: Санкт-Петербург | E19: 1350 | F19: 471 | G19: 208 | H19: 64 | I19: Цена зависит от стоимости объекта | J19: 2026-06-10
A20: Продажа | B20: Городская | C20: Комната | D20: Новосибирск | E20: 1332 | F20: 315 | G20: 148 | H20: 45 | I20: Цена зависит от стоимости объекта | J20: 2026-06-10
A21: Продажа | B21: Городская | C21: Комната | D21: Екатеринбург | E21: 489 | F21: 284 | G21: 155 | H21: 46 | I21: Цена зависит от стоимости объекта | J21: 2026-06-10
A22: Продажа | B22: Городская | C22: Комната | D22: Казань | E22: 315 | F22: 179 | G22: 70 | H22: 20 | I22: Цена зависит от стоимости объекта | J22: 2026-06-10
A23: Продажа | B23: Городская | C23: Комната | D23: Красноярск | E23: 513 | F23: — | G23: — | H23: — | I23: Цена зависит от стоимости объекта | J23: 2026-06-10
A24: Продажа | B24: Городская | C24: Комната | D24: Нижний Новгород | E24: 390 | F24: 159 | G24: 66 | H24: 20 | I24: Цена зависит от стоимости объекта | J24: 2026-06-10
A25: Продажа | B25: Городская | C25: Комната | D25: Челябинск | E25: 171 | F25: 207 | G25: 100 | H25: 29 | I25: Цена зависит от стоимости объекта | J25: 2026-06-10
A26: Продажа | B26: Городская | C26: Комната | D26: Уфа | E26: 225 | F26: 178 | G26: 80 | H26: 23 | I26: Цена зависит от стоимости объекта | J26: 2026-06-10
A27: Продажа | B27: Городская | C27: Комната | D27: Краснодар | E27: 342 | F27: 141 | G27: 60 | H27: 18 | I27: Цена зависит от стоимости объекта | J27: 2026-06-10
A28: Продажа | B28: Городская | C28: Комната | D28: Самара | E28: 192 | F28: — | G28: — | H28: — | I28: Цена зависит от стоимости объекта | J28: 2026-06-10
A29: Продажа | B29: Городская | C29: Комната | D29: Ростов-на-Дону | E29: 468 | F29: 182 | G29: 74 | H29: 22 | I29: Цена зависит от стоимости объекта | J29: 2026-06-10
A30: Продажа | B30: Городская | C30: Комната | D30: Омск | E30: 798 | F30: 345 | G30: 196 | H30: 60 | I30: Цена зависит от стоимости объекта | J30: 2026-06-10
A31: Продажа | B31: Городская | C31: Комната | D31: Воронеж | E31: 126 | F31: — | G31: — | H31: — | I31: Цена зависит от стоимости объекта | J31: 2026-06-10
A32: Продажа | B32: Городская | C32: Комната | D32: Пермь | E32: 99 | F32: — | G32: — | H32: — | I32: Цена зависит от стоимости объекта | J32: 2026-06-10
A33: Продажа | B33: Городская | C33: Комната | D33: Волгоград | E33: 246 | F33: — | G33: — | H33: — | I33: Цена зависит от стоимости объекта | J33: 2026-06-10
A34: Продажа | B34: Городская | C34: Квартира в новостройке | D34: Москва | E34: 3390 | F34: 1213 | G34: 492 | H34: 162 | I34: Цена зависит от стоимости объекта | J34: 2026-06-10
A35: Продажа | B35: Городская | C35: Квартира в новостройке | D35: Санкт-Петербург | E35: 1560 | F35: 538 | G35: 230 | H35: 97 | I35: Цена зависит от стоимости объекта | J35: 2026-06-10
A36: Продажа | B36: Городская | C36: Квартира в новостройке | D36: Новосибирск | E36: 1596 | F36: 357 | G36: 161 | H36: 48 | I36: Цена зависит от стоимости объекта | J36: 2026-06-10
A37: Продажа | B37: Городская | C37: Квартира в новостройке | D37: Екатеринбург | E37: 489 | F37: 390 | G37: 194 | H37: 59 | I37: Цена зависит от стоимости объекта | J37: 2026-06-10
A38: Продажа | B38: Городская | C38: Квартира в новостройке | D38: Казань | E38: 354 | F38: 222 | G38: 86 | H38: 25 | I38: Цена зависит от стоимости объекта | J38: 2026-06-10
A39: Продажа | B39: Городская | C39: Квартира в новостройке | D39: Красноярск | E39: 573 | F39: — | G39: — | H39: — | I39: Цена зависит от стоимости объекта | J39: 2026-06-10
A40: Продажа | B40: Городская | C40: Квартира в новостройке | D40: Нижний Новгород | E40: 441 | F40: 190 | G40: 72 | H40: 22 | I40: Цена зависит от стоимости объекта | J40: 2026-06-10
A41: Продажа | B41: Городская | C41: Квартира в новостройке | D41: Челябинск | E41: 291 | F41: 226 | G41: 105 | H41: 30 | I41: Цена зависит от стоимости объекта | J41: 2026-06-10
A42: Продажа | B42: Городская | C42: Квартира в новостройке | D42: Уфа | E42: 213 | F42: 166 | G42: 76 | H42: 21 | I42: Цена зависит от стоимости объекта | J42: 2026-06-10
A43: Продажа | B43: Городская | C43: Квартира в новостройке | D43: Краснодар | E43: 468 | F43: 167 | G43: 65 | H43: 20 | I43: Цена зависит от стоимости объекта | J43: 2026-06-10
A44: Продажа | B44: Городская | C44: Квартира в новостройке | D44: Самара | E44: 354 | F44: — | G44: — | H44: — | I44: Цена зависит от стоимости объекта | J44: 2026-06-10
A45: Продажа | B45: Городская | C45: Квартира в новостройке | D45: Ростов-на-Дону | E45: 468 | F45: 182 | G45: 74 | H45: 22 | I45: Цена зависит от стоимости объекта | J45: 2026-06-10
A46: Продажа | B46: Городская | C46: Квартира в новостройке | D46: Омск | E46: 780 | F46: 422 | G46: 229 | H46: 70 | I46: Цена зависит от стоимости объекта | J46: 2026-06-10
A47: Продажа | B47: Городская | C47: Квартира в новостройке | D47: Воронеж | E47: 204 | F47: — | G47: — | H47: — | I47: Цена зависит от стоимости объекта | J47: 2026-06-10
A48: Продажа | B48: Городская | C48: Квартира в новостройке | D48: Пермь | E48: 99 | F48: — | G48: — | H48: — | I48: Цена зависит от стоимости объекта | J48: 2026-06-10
A49: Продажа | B49: Городская | C49: Квартира в новостройке | D49: Волгоград | E49: 303 | F49: — | G49: — | H49: — | I49: Цена зависит от стоимости объекта | J49: 2026-06-10
A50: Продажа | B50: Городская | C50: Доля в квартире | D50: Москва | E50: 882 | F50: 1213 | G50: 492 | H50: 162 | I50: Цена зависит от стоимости объекта | J50: 2026-06-10
A51: Продажа | B51: Городская | C51: Доля в квартире | D51: Санкт-Петербург | E51: 1500 | F51: 488 | G51: 207 | H51: 89 | I51: Цена зависит от стоимости объекта | J51: 2026-06-10
A52: Продажа | B52: Городская | C52: Доля в квартире | D52: Новосибирск | E52: 1596 | F52: 420 | G52: 189 | H52: 56 | I52: Цена зависит от стоимости объекта | J52: 2026-06-10
A53: Продажа | B53: Городская | C53: Доля в квартире | D53: Екатеринбург | E53: 489 | F53: 459 | G53: 228 | H53: 69 | I53: Цена зависит от стоимости объекта | J53: 2026-06-10
A54: Продажа | B54: Городская | C54: Доля в квартире | D54: Казань | E54: 354 | F54: 222 | G54: 86 | H54: 25 | I54: Цена зависит от стоимости объекта | J54: 2026-06-10
A55: Продажа | B55: Городская | C55: Доля в квартире | D55: Красноярск | E55: 573 | F55: — | G55: — | H55: — | I55: Цена зависит от стоимости объекта | J55: 2026-06-10
A56: Продажа | B56: Городская | C56: Доля в квартире | D56: Нижний Новгород | E56: 441 | F56: 231 | G56: 90 | H56: 26 | I56: Цена зависит от стоимости объекта | J56: 2026-06-10
A57: Продажа | B57: Городская | C57: Доля в квартире | D57: Челябинск | E57: 291 | F57: 235 | G57: 109 | H57: 31 | I57: Цена зависит от стоимости объекта | J57: 2026-06-10
A58: Продажа | B58: Городская | C58: Доля в квартире | D58: Уфа | E58: 213 | F58: 187 | G58: 87 | H58: 25 | I58: Цена зависит от стоимости объекта | J58: 2026-06-10
A59: Продажа | B59: Городская | C59: Доля в квартире | D59: Краснодар | E59: 468 | F59: 197 | G59: 76 | H59: 23 | I59: Цена зависит от стоимости объекта | J59: 2026-06-10
A60: Продажа | B60: Городская | C60: Доля в квартире | D60: Самара | E60: 354 | F60: — | G60: — | H60: — | I60: Цена зависит от стоимости объекта | J60: 2026-06-10
A61: Продажа | B61: Городская | C61: Доля в квартире | D61: Ростов-на-Дону | E61: 468 | F61: 223 | G61: 90 | H61: 26 | I61: Цена зависит от стоимости объекта | J61: 2026-06-10
A62: Продажа | B62: Городская | C62: Доля в квартире | D62: Омск | E62: 780 | F62: 406 | G62: 220 | H62: 68 | I62: Цена зависит от стоимости объекта | J62: 2026-06-10
A63: Продажа | B63: Городская | C63: Доля в квартире | D63: Воронеж | E63: 204 | F63: — | G63: — | H63: — | I63: Цена зависит от стоимости объекта | J63: 2026-06-10
A64: Продажа | B64: Городская | C64: Доля в квартире | D64: Пермь | E64: 99 | F64: — | G64: — | H64: — | I64: Цена зависит от стоимости объекта | J64: 2026-06-10
A65: Продажа | B65: Городская | C65: Доля в квартире | D65: Волгоград | E65: 303 | F65: — | G65: — | H65: — | I65: Цена зависит от стоимости объекта | J65: 2026-06-10
A66: Продажа | B66: Загородная | C66: Коттедж | D66: Москва | E66: 3090 | F66: 1074 | G66: 437 | H66: 131 | I66: Цена зависит от стоимости объекта | J66: 2026-06-10
A67: Продажа | B67: Загородная | C67: Коттедж | D67: Санкт-Петербург | E67: 783 | F67: 268 | G67: 113 | H67: 36 | I67: Цена зависит от стоимости объекта | J67: 2026-06-10
A68: Продажа | B68: Загородная | C68: Коттедж | D68: Новосибирск | E68: 1149 | F68: 385 | G68: 181 | H68: 54 | I68: Цена зависит от стоимости объекта | J68: 2026-06-10
A69: Продажа | B69: Загородная | C69: Коттедж | D69: Екатеринбург | E69: 813 | F69: 286 | G69: 162 | H69: 48 | I69: Цена зависит от стоимости объекта | J69: 2026-06-10
A70: Продажа | B70: Загородная | C70: Коттедж | D70: Казань | E70: 207 | F70: 169 | G70: 70 | H70: 23 | I70: Цена зависит от стоимости объекта | J70: 2026-06-10
A71: Продажа | B71: Загородная | C71: Коттедж | D71: Красноярск | E71: 258 | F71: — | G71: — | H71: — | I71: Цена зависит от стоимости объекта | J71: 2026-06-10
A72: Продажа | B72: Загородная | C72: Коттедж | D72: Нижний Новгород | E72: 234 | F72: 128 | G72: 54 | H72: 15 | I72: Цена зависит от стоимости объекта | J72: 2026-06-10
A73: Продажа | B73: Загородная | C73: Коттедж | D73: Челябинск | E73: 153 | F73: 226 | G73: 105 | H73: 30 | I73: Цена зависит от стоимости объекта | J73: 2026-06-10
A74: Продажа | B74: Загородная | C74: Коттедж | D74: Уфа | E74: 141 | F74: 131 | G74: 54 | H74: 18 | I74: Цена зависит от стоимости объекта | J74: 2026-06-10
A75: Продажа | B75: Загородная | C75: Коттедж | D75: Краснодар | E75: 210 | F75: 169 | G75: 66 | H75: 19 | I75: Цена зависит от стоимости объекта | J75: 2026-06-10
A76: Продажа | B76: Загородная | C76: Коттедж | D76: Самара | E76: 252 | F76: — | G76: — | H76: — | I76: Цена зависит от стоимости объекта | J76: 2026-06-10
A77: Продажа | B77: Загородная | C77: Коттедж | D77: Ростов-на-Дону | E77: 234 | F77: 172 | G77: 75 | H77: 22 | I77: Цена зависит от стоимости объекта | J77: 2026-06-10
A78: Продажа | B78: Загородная | C78: Коттедж | D78: Омск | E78: 354 | F78: 219 | G78: 102 | H78: 32 | I78: Цена зависит от стоимости объекта | J78: 2026-06-10
A79: Продажа | B79: Загородная | C79: Коттедж | D79: Воронеж | E79: 168 | F79: — | G79: — | H79: — | I79: Цена зависит от стоимости объекта | J79: 2026-06-10
A80: Продажа | B80: Загородная | C80: Коттедж | D80: Пермь | E80: 153 | F80: — | G80: — | H80: — | I80: Цена зависит от стоимости объекта | J80: 2026-06-10
A81: Продажа | B81: Загородная | C81: Коттедж | D81: Волгоград | E81: 111 | F81: — | G81: — | H81: — | I81: Цена зависит от стоимости объекта | J81: 2026-06-10
A82: Продажа | B82: Загородная | C82: Дом/Дача | D82: Москва | E82: 3090 | F82: 1213 | G82: 512 | H82: 155 | I82: Цена зависит от стоимости объекта | J82: 2026-06-10
A83: Продажа | B83: Загородная | C83: Дом/Дача | D83: Санкт-Петербург | E83: 723 | F83: 272 | G83: 115 | H83: 36 | I83: Цена зависит от стоимости объекта | J83: 2026-06-10
A84: Продажа | B84: Загородная | C84: Дом/Дача | D84: Новосибирск | E84: 1050 | F84: 290 | G84: 149 | H84: 45 | I84: Цена зависит от стоимости объекта | J84: 2026-06-10
A85: Продажа | B85: Загородная | C85: Дом/Дача | D85: Екатеринбург | E85: 813 | F85: 317 | G85: 171 | H85: 50 | I85: Цена зависит от стоимости объекта | J85: 2026-06-10
A86: Продажа | B86: Загородная | C86: Дом/Дача | D86: Казань | E86: 207 | F86: 126 | G86: 56 | H86: 18 | I86: Цена зависит от стоимости объекта | J86: 2026-06-10
A87: Продажа | B87: Загородная | C87: Дом/Дача | D87: Красноярск | E87: 270 | F87: — | G87: — | H87: — | I87: Цена зависит от стоимости объекта | J87: 2026-06-10
A88: Продажа | B88: Загородная | C88: Дом/Дача | D88: Нижний Новгород | E88: 207 | F88: 118 | G88: 48 | H88: 14 | I88: Цена зависит от стоимости объекта | J88: 2026-06-10
A89: Продажа | B89: Загородная | C89: Дом/Дача | D89: Челябинск | E89: 258 | F89: 184 | G89: 89 | H89: 26 | I89: Цена зависит от стоимости объекта | J89: 2026-06-10
A90: Продажа | B90: Загородная | C90: Дом/Дача | D90: Уфа | E90: 234 | F90: 115 | G90: 48 | H90: 15 | I90: Цена зависит от стоимости объекта | J90: 2026-06-10
A91: Продажа | B91: Загородная | C91: Дом/Дача | D91: Краснодар | E91: 150 | F91: 170 | G91: 67 | H91: 20 | I91: Цена зависит от стоимости объекта | J91: 2026-06-10
A92: Продажа | B92: Загородная | C92: Дом/Дача | D92: Самара | E92: 225 | F92: — | G92: — | H92: — | I92: Цена зависит от стоимости объекта | J92: 2026-06-10
A93: Продажа | B93: Загородная | C93: Дом/Дача | D93: Ростов-на-Дону | E93: 234 | F93: 154 | G93: 63 | H93: 20 | I93: Цена зависит от стоимости объекта | J93: 2026-06-10
A94: Продажа | B94: Загородная | C94: Дом/Дача | D94: Омск | E94: 354 | F94: 200 | G94: 97 | H94: 31 | I94: Цена зависит от стоимости объекта | J94: 2026-06-10
A95: Продажа | B95: Загородная | C95: Дом/Дача | D95: Воронеж | E95: 99 | F95: — | G95: — | H95: — | I95: Цена зависит от стоимости объекта | J95: 2026-06-10
A96: Продажа | B96: Загородная | C96: Дом/Дача | D96: Пермь | E96: 168 | F96: — | G96: — | H96: — | I96: Цена зависит от стоимости объекта | J96: 2026-06-10
A97: Продажа | B97: Загородная | C97: Дом/Дача | D97: Волгоград | E97: 273 | F97: — | G97: — | H97: — | I97: Цена зависит от стоимости объекта | J97: 2026-06-10
A98: Продажа | B98: Загородная | C98: Таунхаус | D98: Москва | E98: 3090 | F98: 1031 | G98: 418 | H98: 125 | I98: Цена зависит от стоимости объекта | J98: 2026-06-10
A99: Продажа | B99: Загородная | C99: Таунхаус | D99: Санкт-Петербург | E99: 783 | F99: 204 | G99: 89 | H99: 26 | I99: Цена зависит от стоимости объекта | J99: 2026-06-10
A100: Продажа | B100: Загородная | C100: Таунхаус | D100: Новосибирск | E100: 1200 | F100: 353 | G100: 164 | H100: 50 | I100: Цена зависит от стоимости объекта | J100: 2026-06-10
...

Sheet Яндекс
A1: Группа | B1: Категория | C1: Город | D1: 2026-06-11
A2: Купить | B2: Квартира | C2: 🇷🇺 Вся Россия | D2: 925191
A3: Купить | B3: Квартира | C3: Москва | D3: 69187
A4: Купить | B4: Квартира | C4: Санкт-Петербург | D4: 39444
A5: Купить | B5: Квартира | C5: Новосибирск | D5: 31864
A6: Купить | B6: Квартира | C6: Екатеринбург | D6: 38343
A7: Купить | B7: Квартира | C7: Казань | D7: 18334
A8: Купить | B8: Квартира | C8: Красноярск | D8: —
A9: Купить | B9: Квартира | C9: Нижний Новгород | D9: 10203
A10: Купить | B10: Квартира | C10: Челябинск | D10: 6426
A11: Купить | B11: Квартира | C11: Уфа | D11: 18896
A12: Купить | B12: Квартира | C12: Краснодар | D12: 68429
A13: Купить | B13: Квартира | C13: Самара | D13: 6124
A14: Купить | B14: Квартира | C14: Ростов-на-Дону | D14: 46684
A15: Купить | B15: Квартира | C15: Омск | D15: 5009
A16: Купить | B16: Квартира | C16: Воронеж | D16: 13990
A17: Купить | B17: Квартира | C17: Пермь | D17: 14018
A18: Купить | B18: Квартира | C18: Волгоград | D18: 8860
A19: Купить | B19: Квартира в новостройке | C19: 🇷🇺 Вся Россия | D19: 547731
A20: Купить | B20: Квартира в новостройке | C20: Москва | D20: 48774
... A239: Коммерческая | B239: Аренда | C239: Волгоград | D239: 462
A241: Итого (по фильтру) | C241: ← сумма видимых строк (без «Вся Россия») | D241: =SUMPRODUCT(SUBTOTAL(109,OFFSET(D$2,ROW(D$2:D$239)-ROW(D$2),0)),--($C$2:$C$239<>"🇷🇺 Вся Россия"))

Sheet Авито
A1: Группа | B1: Категория | C1: Город | D1: 2026-06-11 | E1: 2026-06-12
A2: Продажа | B2: Квартиры | C2: 🇷🇺 Вся Россия | D2: 1475674 | E2: 1463127
A3: Продажа | B3: Квартиры | C3: Москва | D3: 69503 | E3: 69897
A4: Продажа | B4: Квартиры | C4: Санкт-Петербург | D4: 59698 | E4: 59674
A5: Продажа | B5: Квартиры | C5: Новосибирск | D5: 25738 | E5: 26305
A6: Продажа | B6: Квартиры | C6: Екатеринбург | D6: 51974 | E6: 51802
A7: Продажа | B7: Квартиры | C7: Казань | D7: 28365 | E7: 28308
A8: Продажа | B8: Квартиры | C8: Красноярск | D8: 20160 | E8: 20148
A9: Продажа | B9: Квартиры | C9: Нижний Новгород | D9: 12294 | E9: 12413
A10: Продажа | B10: Квартиры | C10: Челябинск | D10: 17205 | E10: 15543
A11: Продажа | B11: Квартиры | C11: Уфа | D11: 24237 | E11: 24198
A12: Продажа | B12: Квартиры | C12: Краснодар | D12: 66810 | E12: 66651
A13: Продажа | B13: Квартиры | C13: Самара | D13: 8317 | E13: 8301
... A137: Аренда | B137: Квартиры | C137: Волгоград | D137: 5196 | E137: 5182
A138: Аренда | B138: Квартиры долгосрочно | C138: 🇷🇺 Вся Россия | E138: 170002
A139: Аренда | B139: Квартиры долгосрочно | C139: Москва | E139: 17890
A140: Аренда | B140: Квартиры долгосрочно | C140: Санкт-Петербург | E140: 11104
A141: Аренда | B141: Квартиры долгосрочно | C141: Новосибирск | E141: 6016
A142: Аренда | B142: Квартиры долгосрочно | C142: Екатеринбург | E142: 5202
A143: Аренда | B143: Квартиры долгосрочно | C143: Казань | E143: 3609
A144: Аренда | B144: Квартиры долгосрочно | C144: Красноярск | E144: 1625
A145: Аренда | B145: Квартиры долгосрочно | C145: Нижний Новгород | E145: 1881
A146: Аренда | B146: Квартиры долгосрочно | C146: Челябинск | E146: 2436
A147: Аренда | B147: Квартиры долгосрочно | C147: Уфа | E147: 2918
A148: Аренда | B148: Квартиры долгосрочно | C148: Краснодар | E148: 7626
A149: Аренда | B149: Квартиры долгосрочно | C149: Самара | E149: 1837
... A171: Аренда | B171: Квартиры посуточно | C171: Волгоград | E171: 3881
A172: Аренда | B172: Комнаты | C172: 🇷🇺 Вся Россия | D172: 35488 | E172: 35399
A173: Аренда | B173: Комнаты | C173: Москва | D173: 6047 | E173: 5967
A174: Аренда | B174: Комнаты | C174: Санкт-Петербург | D174: 2003 | E174: 1990
A175: Аренда | B175: Комнаты | C175: Новосибирск | D175: 431 | E175: 431
A176: Аренда | B176: Комнаты | C176: Екатеринбург | D176: 527 | E176: 532
A177: Аренда | B177: Комнаты | C177: Казань | D177: 337 | E177: 337
A178: Аренда | B178: Комнаты | C178: Красноярск | D178: 147 | E178: 141
A179: Аренда | B179: Комнаты | C179: Нижний Новгород | D179: 216 | E179: 216
A180: Аренда | B180: Комнаты | C180: Челябинск | D180: 166 | E180: 162
A181: Аренда | B181: Комнаты | C181: Уфа | D181: 171 | E181: 169
A182: Аренда | B182: Комнаты | C182: Краснодар | D182: 342 | E182: 337
A183: Аренда | B183: Комнаты | C183: Самара | D183: 197 | E183: 194
... A239: Аренда | B239: Коммерческая | C239: Волгоград | D239: 1000 | E239: 983
A241: Итого (по фильтру) | C241: ← сумма видимых строк (без «Вся Россия») | D241: =SUMPRODUCT(SUBTOTAL(109,OFFSET(D$2,ROW(D$2:D$239)-ROW(D$2),0)),--($C$2:$C$239<>"🇷🇺 Вся Россия")) | E241: =SUMPRODUCT(SUBTOTAL(109,OFFSET(E$2,ROW(E$2:E$239)-ROW(E$2),0)),--($C$2:$C$239<>"🇷🇺 Вся Россия"))

Sheet Яндекс регионы
A1: Группа | B1: Категория | C1: Регион | D1: 2026-06-11
A2: Купить | B2: Квартира | C2: Адыгея | D2: 9474
A3: Купить | B3: Квартира | C3: Алтай | D3: 787
A4: Купить | B4: Квартира | C4: Алтайский | D4: 3525
A5: Купить | B5: Квартира | C5: Амурская | D5: 1985
A6: Купить | B6: Квартира | C6: Архангельская | D6: 4850
A7: Купить | B7: Квартира | C7: Астраханская | D7: 5302
A8: Купить | B8: Квартира | C8: Башкортостан | D8: 23898
A9: Купить | B9: Квартира | C9: Белгородская | D9: 5343
A10: Купить | B10: Квартира | C10: Брянская | D10: 4668
A11: Купить | B11: Квартира | C11: Бурятия | D11: 2663
A12: Купить | B12: Квартира | C12: Владимирская | D12: 7918
A13: Купить | B13: Квартира | C13: Волгоградская | D13: 9605
... A1191: Коммерческая | B1191: Аренда | C1191: Ярославская | D1191: 840
A1193: Итого (по фильтру) | C1193: ← сумма видимых строк | D1193: =SUBTOTAL(109,D2:D1191)

Sheet Домклик
A1: Группа | B1: Категория | C1: Город | D1: 2026-06-11 | E1: 2026-06-12
A2: Покупка | B2: Квартиры | C2: 🇷🇺 Вся Россия | D2: 724157 | E2: 720954
A3: Покупка | B3: Квартиры | C3: Москва | D3: 64176
A4: Покупка | B4: Квартиры | C4: Санкт-Петербург | D4: 48234
A5: Покупка | B5: Квартиры | C5: Новосибирск | D5: 23764
A6: Покупка | B6: Квартиры | C6: Екатеринбург | D6: 35000
A7: Покупка | B7: Квартиры | C7: Казань | D7: 14529
A8: Покупка | B8: Квартиры | C8: Красноярск | D8: 14189
A9: Покупка | B9: Квартиры | C9: Нижний Новгород | D9: 9212
A10: Покупка | B10: Квартиры | C10: Челябинск | D10: 10811
A11: Покупка | B11: Квартиры | C11: Уфа | D11: 22529
A12: Покупка | B12: Квартиры | C12: Краснодар | D12: 48810
A13: Покупка | B13: Квартиры | C13: Самара | D13: 10363
A14: Покупка | B14: Квартиры | C14: Ростов-на-Дону | D14: 31328
... A18: Покупка | B18: Квартиры | C18: Волгоград | D18: 8713
A19: Покупка | B19: Квартиры вторичка | C19: 🇷🇺 Вся Россия | D19: 261742 | E19: 258987
A20: Покупка | B20: Квартиры вторичка | C20: Москва | D20: 20462
A21: Покупка | B21: Квартиры вторичка | C21: Санкт-Петербург | D21: 16593
A22: Покупка | B22: Квартиры вторичка | C22: Новосибирск | D22: 8041
A23: Покупка | B23: Квартиры вторичка | C23: Екатеринбург | D23: 6619
A24: Покупка | B24: Квартиры вторичка | C24: Казань | D24: 3572
A25: Покупка | B25: Квартиры вторичка | C25: Красноярск | D25: 5153
A26: Покупка | B26: Квартиры вторичка | C26: Нижний Новгород | D26: 3773
A27: Покупка | B27: Квартиры вторичка | C27: Челябинск | D27: 3897
A28: Покупка | B28: Квартиры вторичка | C28: Уфа | D28: 4582
A29: Покупка | B29: Квартиры вторичка | C29: Краснодар | D29: 14192
A30: Покупка | B30: Квартиры вторичка | C30: Самара | D30: 3440
A31: Покупка | B31: Квартиры вторичка | C31: Ростов-на-Дону | D31: 9162
... A35: Покупка | B35: Квартиры вторичка | C35: Волгоград | D35: 4113
A36: Покупка | B36: Квартиры новостройки | C36: 🇷🇺 Вся Россия | D36: 462416 | E36: 462371
A37: Покупка | B37: Квартиры новостройки | C37: Москва | D37: 43714
A38: Покупка | B38: Квартиры новостройки | C38: Санкт-Петербург | D38: 31641
A39: Покупка | B39: Квартиры новостройки | C39: Новосибирск | D39: 15723
A40: Покупка | B40: Квартиры новостройки | C40: Екатеринбург | D40: 28381
A41: Покупка | B41: Квартиры новостройки | C41: Казань | D41: 10957
A42: Покупка | B42: Квартиры новостройки | C42: Красноярск | D42: 9036
A43: Покупка | B43: Квартиры новостройки | C43: Нижний Новгород | D43: 5439
A44: Покупка | B44: Квартиры новостройки | C44: Челябинск | D44: 6914
A45: Покупка | B45: Квартиры новостройки | C45: Уфа | D45: 17947
A46: Покупка | B46: Квартиры новостройки | C46: Краснодар | D46: 34618
A47: Покупка | B47: Квартиры новостройки | C47: Самара | D47: 6923
A48: Покупка | B48: Квартиры новостройки | C48: Ростов-на-Дону | D48: 22166
... A52: Покупка | B52: Квартиры новостройки | C52: Волгоград | D52: 4600
A53: Покупка | B53: Комнаты | C53: 🇷🇺 Вся Россия | D53: 11955 | E53: 11833
A54: Покупка | B54: Комнаты | C54: Москва | D54: 537
A55: Покупка | B55: Комнаты | C55: Санкт-Петербург | D55: 1736
A56: Покупка | B56: Комнаты | C56: Новосибирск | D56: 419
A57: Покупка | B57: Комнаты | C57: Екатеринбург | D57: 486
A58: Покупка | B58: Комнаты | C58: Казань | D58: 174
A59: Покупка | B59: Комнаты | C59: Красноярск | D59: 260
A60: Покупка | B60: Комнаты | C60: Нижний Новгород | D60: 254
A61: Покупка | B61: Комнаты | C61: Челябинск | D61: 91
A62: Покупка | B62: Комнаты | C62: Уфа | D62: 287
A63: Покупка | B63: Комнаты | C63: Краснодар | D63: 130
A64: Покупка | B64: Комнаты | C64: Самара | D64: 118
A65: Покупка | B65: Комнаты | C65: Ростов-на-Дону | D65: 165
... A69: Покупка | B69: Комнаты | C69: Волгоград | D69: 299
A70: Покупка | B70: Дом | C70: 🇷🇺 Вся Россия | D70: 107418 | E70: 107247
A71: Покупка | B71: Дом | C71: Москва | D71: 1933
A72: Покупка | B72: Дом | C72: Санкт-Петербург | D72: 940
A73: Покупка | B73: Дом | C73: Новосибирск | D73: 2237
A74: Покупка | B74: Дом | C74: Екатеринбург | D74: 1598
A75: Покупка | B75: Дом | C75: Казань | D75: 1794
A76: Покупка | B76: Дом | C76: Красноярск | D76: 1324
A77: Покупка | B77: Дом | C77: Нижний Новгород | D77: 837
A78: Покупка | B78: Дом | C78: Челябинск | D78: 907
A79: Покупка | B79: Дом | C79: Уфа | D79: 3525
A80: Покупка | B80: Дом | C80: Краснодар | D80: 14780
A81: Покупка | B81: Дом | C81: Самара | D81: 861
A82: Покупка | B82: Дом | C82: Ростов-на-Дону | D82: 6213
... A86: Покупка | B86: Дом | C86: Волгоград | D86: 1675
A87: Покупка | B87: Дача | C87: 🇷🇺 Вся Россия | D87: 105220 | E87: 105063
A88: Покупка | B88: Дача | C88: Москва | D88: 1843
A89: Покупка | B89: Дача | C89: Санкт-Петербург | D89: 917
A90: Покупка | B90: Дача | C90: Новосибирск | D90: 2210
A91: Покупка | B91: Дача | C91: Екатеринбург | D91: 1582
A92: Покупка | B92: Дача | C92: Казань | D92: 1781
A93: Покупка | B93: Дача | C93: Красноярск | D93: 1293
A94: Покупка | B94: Дача | C94: Нижний Новгород | D94: 824
A95: Покупка | B95: Дача | C95: Челябинск | D95: 896
A96: Покупка | B96: Дача | C96: Уфа | D96: 3497
A97: Покупка | B97: Дача | C97: Краснодар | D97: 14491
A98: Покупка | B98: Дача | C98: Самара | D98: 828
A99: Покупка | B99: Дача | C99: Ростов-на-Дону | D99: 6034
... A103: Покупка | B103: Дача | C103: Волгоград | D103: 1660
A104: Покупка | B104: Коттеджи | C104: 🇷🇺 Вся Россия | D104: 28020 | E104: 28012
A105: Покупка | B105: Коттеджи | C105: Москва | D105: 1356
A106: Покупка | B106: Коттеджи | C106: Санкт-Петербург | D106: 587
A107: Покупка | B107: Коттеджи | C107: Новосибирск | D107: 556
A108: Покупка | B108: Коттеджи | C108: Екатеринбург | D108: 409
A109: Покупка | B109: Коттеджи | C109: Казань | D109: 604
A110: Покупка | B110: Коттеджи | C110: Красноярск | D110: 416
A111: Покупка | B111: Коттеджи | C111: Нижний Новгород | D111: 315
A112: Покупка | B112: Коттеджи | C112: Челябинск | D112: 211
A113: Покупка | B113: Коттеджи | C113: Уфа | D113: 989
A114: Покупка | B114: Коттеджи | C114: Краснодар | D114: 3302
A115: Покупка | B115: Коттеджи | C115: Самара | D115: 344
A116: Покупка | B116: Коттеджи | C116: Ростов-на-Дону | D116: 1006
... A120: Покупка | B120: Коттеджи | C120: Волгоград | D120: 366
A121: Покупка | B121: Таунхаусы | C121: 🇷🇺 Вся Россия | D121: 3673 | E121: 3674
...

Sheet Домклик города (РФ)
A1: Группа | B1: Категория | C1: Город | D1: 2026-06-12
A2: Покупка | B2: Квартиры | C2: Абакан | D2: 3889
A3: Покупка | B3: Квартиры | C3: Анадырь | D3: 43
A4: Покупка | B4: Квартиры | C4: Архангельск | D4: 5313
A5: Покупка | B5: Квартиры | C5: Астрахань | D5: 9000
A6: Покупка | B6: Квартиры | C6: Балашиха | D6: 3215
A7: Покупка | B7: Квартиры | C7: Барнаул | D7: 3333
A8: Покупка | B8: Квартиры | C8: Белгород | D8: 3204
A9: Покупка | B9: Квартиры | C9: Биробиджан | D9: 138
A10: Покупка | B10: Квартиры | C10: Благовещенск | D10: 1611
A11: Покупка | B11: Квартиры | C11: Братск | D11: 688
A12: Покупка | B12: Квартиры | C12: Брянск | D12: 3695
A13: Покупка | B13: Квартиры | C13: Чебоксары | D13: 2705
... A2120: Аренда | B2120: Коммерческая | C2120: Жуковский | D2120: 144
A2122: Итого (по фильтру) | C2122: ← сумма видимых строк | D2122: =SUBTOTAL(109,D2:D2120)

Sheet Avito Price
A1: Город | B1: Публикация 14 дн | C1: Публикация 30 дн | D1: Публикация 60 дн | E1: Продвижение: Оценить (5 дн) | F1: Продвижение: Выбирают чаще (5 дн) | G1: Продвижение: Сильнее (5 дн) | H1: Выделение цветом (7 дн) | I1: XL (7 дн) | J1: Обновлено
A2: Москва | B2: 641 | C2: 856 | D2: 1540 | E2: 1660 | F2: 3215 | G2: 6505 | H2: 373 | I2: 373 | J2: 2026-06-16
A3: Санкт-Петербург | B3: 1435 | C3: 1915 | D3: 3446 | E3: 1460 | F3: 2850 | G3: 5765 | H3: 329 | I3: 329 | J3: 2026-06-16
A4: Новосибирск | B4: 1378 | C4: 1836 | D4: 3305 | E4: 1255 | F4: 2465 | G4: 4940 | H4: 285 | I4: 285 | J4: 2026-06-16
A5: Екатеринбург | B5: 1282 | C5: 1708 | D5: 3073 | E5: 1255 | F5: 2465 | G5: 4940 | H5: 285 | I5: 285 | J5: 2026-06-16
A6: Казань | B6: 1625 | C6: 2167 | D6: 3900 | E6: 1515 | F6: 3060 | G6: 6175 | H6: 351 | I6: 351 | J6: 2026-06-16
A7: Красноярск | B7: 1949 | C7: 2600 | D7: 4677 | E7: 965 | F7: 1915 | G7: 3865 | H7: 219 | I7: 219 | J7: 2026-06-16
A8: Нижний Новгород | B8: 1249 | C8: 1666 | D8: 3001 | E8: 1165 | F8: 2280 | G8: 4610 | H8: 263 | I8: 263 | J8: 2026-06-16
A9: Челябинск | B9: 1810 | C9: 2410 | D9: 4340 | E9: 1255 | F9: 2465 | G9: 4940 | H9: 285 | I9: 285 | J9: 2026-06-16
A10: Уфа | B10: 1361 | C10: 1814 | D10: 3268 | E10: 1515 | F10: 3060 | G10: 6175 | H10: 351 | I10: 351 | J10: 2026-06-16
A11: Краснодар | B11: 2105 | C11: 2806 | D11: 5053 | E11: 1605 | F11: 3140 | G11: 6340 | H11: 362 | I11: 362 | J11: 2026-06-16
A12: Самара | B12: 1319 | C12: 1757 | D12: 3163 | E12: 1165 | F12: 2280 | G12: 4610 | H12: 351 | I12: 351 | J12: 2026-06-16
A13: Ростов-на-Дону | B13: 1607 | C13: 2144 | D13: 3859 | E13: 1220 | F13: 2355 | G13: 4775 | H13: 274 | I13: 274 | J13: 2026-06-16
... A17: Волгоград | B17: 1419 | C17: 1891 | D17: 3406 | E17: 1365 | F17: 2645 | G17: 5350 | H17: 307 | I17: 307 | J17: 2026-06-16

Sheet Динамика цен
A1: Источник | B1: Город | C1: Категория | D1: Тип цены | E1: июн.2026 | F1: Δ%
A2: Avito | B2: Москва | D2: Публикация 14 дн | E2: 641
A3: Avito | B3: Москва | D3: Публикация 30 дн | E3: 856
A4: Avito | B4: Москва | D4: Публикация 60 дн | E4: 1540
A5: Avito | B5: Москва | D5: Продвижение: Оценить (5 дн) | E5: 1660
A6: Avito | B6: Москва | D6: Продвижение: Выбирают чаще (5 дн) | E6: 3215
A7: Avito | B7: Москва | D7: Продвижение: Сильнее (5 дн) | E7: 6505
A8: Avito | B8: Москва | D8: Выделение цветом (7 дн) | E8: 373
A9: Avito | B9: Москва | D9: XL (7 дн) | E9: 373
A10: Avito | B10: Санкт-Петербург | D10: Публикация 14 дн | E10: 1435
A11: Avito | B11: Санкт-Петербург | D11: Публикация 30 дн | E11: 1915
A12: Avito | B12: Санкт-Петербург | D12: Публикация 60 дн | E12: 3446
A13: Avito | B13: Санкт-Петербург | D13: Продвижение: Оценить (5 дн) | E13: 1460
... A129: Avito | B129: Волгоград | D129: XL (7 дн) | E129: 307
A130: CIAN | B130: Москва | C130: Продажа · Городская · Квартира | D130: Публикация, ₽/30 дн | E130: 3390
A131: CIAN | B131: Москва | C131: Продажа · Городская · Квартира | D131: Топ, ₽/сут | E131: 1213
A132: CIAN | B132: Москва | C132: Продажа · Городская · Квартира | D132: Премиум, ₽/сут | E132: 492
A133: CIAN | B133: Москва | C133: Продажа · Городская · Квартира | D133: Стандарт, ₽/сут | E133: 162
A134: CIAN | B134: Санкт-Петербург | C134: Продажа · Городская · Квартира | D134: Публикация, ₽/30 дн | E134: 1560
A135: CIAN | B135: Санкт-Петербург | C135: Продажа · Городская · Квартира | D135: Топ, ₽/сут | E135: 598
A136: CIAN | B136: Санкт-Петербург | C136: Продажа · Городская · Квартира | D136: Премиум, ₽/сут | E136: 255
A137: CIAN | B137: Санкт-Петербург | C137: Продажа · Городская · Квартира | D137: Стандарт, ₽/сут | E137: 108
A138: CIAN | B138: Новосибирск | C138: Продажа · Городская · Квартира | D138: Публикация, ₽/30 дн | E138: 1596
A139: CIAN | B139: Новосибирск | C139: Продажа · Городская · Квартира | D139: Топ, ₽/сут | E139: 420
A140: CIAN | B140: Новосибирск | C140: Продажа · Городская · Квартира | D140: Премиум, ₽/сут | E140: 189
A141: CIAN | B141: Новосибирск | C141: Продажа · Городская · Квартира | D141: Стандарт, ₽/сут | E141: 56
... A150: CIAN | B150: Красноярск | C150: Продажа · Городская · Квартира | D150: Публикация, ₽/30 дн | E150: 573
A151: CIAN | B151: Красноярск | C151: Продажа · Городская · Квартира | D151: Топ, ₽/сут | E151: —
A152: CIAN | B152: Красноярск | C152: Продажа · Городская · Квартира | D152: Премиум, ₽/сут | E152: —
A153: CIAN | B153: Красноярск | C153: Продажа · Городская · Квартира | D153: Стандарт, ₽/сут | E153: —
A154: CIAN | B154: Нижний Новгород | C154: Продажа · Городская · Квартира | D154: Публикация, ₽/30 дн | E154: 441
A155: CIAN | B155: Нижний Новгород | C155: Продажа · Городская · Квартира | D155: Топ, ₽/сут | E155: 208
A156: CIAN | B156: Нижний Новгород | C156: Продажа · Городская · Квартира | D156: Премиум, ₽/сут | E156: 81
A157: CIAN | B157: Нижний Новгород | C157: Продажа · Городская · Квартира | D157: Стандарт, ₽/сут | E157: 23
A158: CIAN | B158: Челябинск | C158: Продажа · Городская · Квартира | D158: Публикация, ₽/30 дн | E158: 291
A159: CIAN | B159: Челябинск | C159: Продажа · Городская · Квартира | D159: Топ, ₽/сут | E159: 203
A160: CIAN | B160: Челябинск | C160: Продажа · Городская · Квартира | D160: Премиум, ₽/сут | E160: 95
A161: CIAN | B161: Челябинск | C161: Продажа · Городская · Квартира | D161: Стандарт, ₽/сут | E161: 27
A162: CIAN | B162: Уфа | C162: Продажа · Городская · Квартира | D162: Публикация, ₽/30 дн | E162: 213
A163: CIAN | B163: Уфа | C163: Продажа · Городская · Квартира | D163: Топ, ₽/сут | E163: 176
A164: CIAN | B164: Уфа | C164: Продажа · Городская · Квартира | D164: Премиум, ₽/сут | E164: 80
A165: CIAN | B165: Уфа | C165: Продажа · Городская · Квартира | D165: Стандарт, ₽/сут | E165: 23
... A170: CIAN | B170: Самара | C170: Продажа · Городская · Квартира | D170: Публикация, ₽/30 дн | E170: 354
A171: CIAN | B171: Самара | C171: Продажа · Городская · Квартира | D171: Топ, ₽/сут | E171: —
A172: CIAN | B172: Самара | C172: Продажа · Городская · Квартира | D172: Премиум, ₽/сут | E172: —
A173: CIAN | B173: Самара | C173: Продажа · Городская · Квартира | D173: Стандарт, ₽/сут | E173: —
A174: CIAN | B174: Ростов-на-Дону | C174: Продажа · Городская · Квартира | D174: Публикация, ₽/30 дн | E174: 468
A175: CIAN | B175: Ростов-на-Дону | C175: Продажа · Городская · Квартира | D175: Топ, ₽/сут | E175: 214
A176: CIAN | B176: Ростов-на-Дону | C176: Продажа · Городская · Квартира | D176: Премиум, ₽/сут | E176: 87
A177: CIAN | B177: Ростов-на-Дону | C177: Продажа · Городская · Квартира | D177: Стандарт, ₽/сут | E177: 26
A178: CIAN | B178: Омск | C178: Продажа · Городская · Квартира | D178: Публикация, ₽/30 дн | E178: 780
A179: CIAN | B179: Омск | C179: Продажа · Городская · Квартира | D179: Топ, ₽/сут | E179: 345
A180: CIAN | B180: Омск | C180: Продажа · Городская · Квартира | D180: Премиум, ₽/сут | E180: 187
A181: CIAN | B181: Омск | C181: Продажа · Городская · Квартира | D181: Стандарт, ₽/сут | E181: 58
A182: CIAN | B182: Воронеж | C182: Продажа · Городская · Квартира | D182: Публикация, ₽/30 дн | E182: 204
A183: CIAN | B183: Воронеж | C183: Продажа · Городская · Квартира | D183: Топ, ₽/сут | E183: —
A184: CIAN | B184: Воронеж | C184: Продажа · Городская · Квартира | D184: Премиум, ₽/сут | E184: —
A185: CIAN | B185: Воронеж | C185: Продажа · Городская · Квартира | D185: Стандарт, ₽/сут | E185: —
A186: CIAN | B186: Пермь | C186: Продажа · Городская · Квартира | D186: Публикация, ₽/30 дн | E186: 99
A187: CIAN | B187: Пермь | C187: Продажа · Городская · Квартира | D187: Топ, ₽/сут | E187: —
A188: CIAN | B188: Пермь | C188: Продажа · Городская · Квартира | D188: Премиум, ₽/сут | E188: —
A189: CIAN | B189: Пермь | C189: Продажа · Городская · Квартира | D189: Стандарт, ₽/сут | E189: —
A190: CIAN | B190: Волгоград | C190: Продажа · Городская · Квартира | D190: Публикация, ₽/30 дн | E190: 303
A191: CIAN | B191: Волгоград | C191: Продажа · Городская · Квартира | D191: Топ, ₽/сут | E191: —
A192: CIAN | B192: Волгоград | C192: Продажа · Городская · Квартира | D192: Премиум, ₽/сут | E192: —
A193: CIAN | B193: Волгоград | C193: Продажа · Городская · Квартира | D193: Стандарт, ₽/сут | E193: —
A194: CIAN | B194: Москва | C194: Продажа · Городская · Комната | D194: Публикация, ₽/30 дн | E194: 3120
A195: CIAN | B195: Москва | C195: Продажа · Городская · Комната | D195: Топ, ₽/сут | E195: 904
A196: CIAN | B196: Москва | C196: Продажа · Городская · Комната | D196: Премиум, ₽/сут | E196: 382
A197: CIAN | B197: Москва | C197: Продажа · Городская · Комната | D197: Стандарт, ₽/сут | E197: 116
A198: CIAN | B198: Санкт-Петербург | C198: Продажа · Городская · Комната | D198: Публикация, ₽/30 дн | E198: 1350
A199: CIAN | B199: Санкт-Петербург | C199: Продажа · Городская · Комната | D199: Топ, ₽/сут | E199: 471
A200: CIAN | B200: Санкт-Петербург | C200: Продажа · Городская · Комната | D200: Премиум, ₽/сут | E200: 208
A201: CIAN | B201: Санкт-Петербург | C201: Продажа · Городская · Комната | D201: Стандарт, ₽/сут | E201: 64
A202: CIAN | B202: Новосибирск | C202: Продажа · Городская · Комната | D202: Публикация, ₽/30 дн | E202: 1332
A203: CIAN | B203: Новосибирск | C203: Продажа · Городская · Комната | D203: Топ, ₽/сут | E203: 315
A204: CIAN | B204: Новосибирск | C204: Продажа · Городская · Комната | D204: Премиум, ₽/сут | E204: 148
A205: CIAN | B205: Новосибирск | C205: Продажа · Городская · Комната | D205: Стандарт, ₽/сут | E205: 45
... A214: CIAN | B214: Красноярск | C214: Продажа · Городская · Комната | D214: Публикация, ₽/30 дн | E214: 513
A215: CIAN | B215: Красноярск | C215: Продажа · Городская · Комната | D215: Топ, ₽/сут | E215: —
A216: CIAN | B216: Красноярск | C216: Продажа · Городская · Комната | D216: Премиум, ₽/сут | E216: —
A217: CIAN | B217: Красноярск | C217: Продажа · Городская · Комната | D217: Стандарт, ₽/сут | E217: —
A218: CIAN | B218: Нижний Новгород | C218: Продажа · Городская · Комната | D218: Публикация, ₽/30 дн | E218: 390
A219: CIAN | B219: Нижний Новгород | C219: Продажа · Городская · Комната | D219: Топ, ₽/сут | E219: 159
A220: CIAN | B220: Нижний Новгород | C220: Продажа · Городская · Комната | D220: Премиум, ₽/сут | E220: 66
A221: CIAN | B221: Нижний Новгород | C221: Продажа · Городская · Комната | D221: Стандарт, ₽/сут | E221: 20
A222: CIAN | B222: Челябинск | C222: Продажа · Городская · Комната | D222: Публикация, ₽/30 дн | E222: 171
A223: CIAN | B223: Челябинск | C223: Продажа · Городская · Комната | D223: Топ, ₽/сут | E223: 207
A224: CIAN | B224: Челябинск | C224: Продажа · Городская · Комната | D224: Премиум, ₽/сут | E224: 100
A225: CIAN | B225: Челябинск | C225: Продажа · Городская · Комната | D225: Стандарт, ₽/сут | E225: 29
A226: CIAN | B226: Уфа | C226: Продажа · Городская · Комната | D226: Публикация, ₽/30 дн | E226: 225
A227: CIAN | B227: Уфа | C227: Продажа · Городская · Комната | D227: Топ, ₽/сут | E227: 178
A228: CIAN | B228: Уфа | C228: Продажа · Городская · Комната | D228: Премиум, ₽/сут | E228: 80
A229: CIAN | B229: Уфа | C229: Продажа · Городская · Комната | D229: Стандарт, ₽/сут | E229: 23
... A234: CIAN | B234: Самара | C234: Продажа · Городская · Комната | D234: Публикация, ₽/30 дн | E234: 192
A235: CIAN | B235: Самара | C235: Продажа · Городская · Комната | D235: Топ, ₽/сут | E235: —
A236: CIAN | B236: Самара | C236: Продажа · Городская · Комната | D236: Премиум, ₽/сут | E236: —
A237: CIAN | B237: Самара | C237: Продажа · Городская · Комната | D237: Стандарт, ₽/сут | E237: —
A238: CIAN | B238: Ростов-на-Дону | C238: Продажа · Городская · Комната | D238: Публикация, ₽/30 дн | E238: 468
A239: CIAN | B239: Ростов-на-Дону | C239: Продажа · Городская · Комната | D239: Топ, ₽/сут | E239: 182
...
